Workbook

Sheet comps -raw
B2: Gems, Jewellery And Watches Companies
B3: 94 results found: Showing page 1 of 4
B4: Export
B5: Edit Columns
B6: S.No. | C6: Name | D6: CMP Rs. | E6: Mar Cap Rs.Cr. | F6: Debt Rs.Cr. | G6: Debt / Eq
B7: 1 | C7: Titan Company | D7: 3953.2 | E7: 350493.51 | F7: 12465 | G7: 0.97
B8: 2 | C8: Kalyan Jewellers | D8: 365.5 | E8: 37754.06 | F8: 5334.96 | G8: 1
B9: 3 | C9: Thangamayil Jew. | D9: 3218.9 | E9: 10008.14 | F9: 1124.35 | G9: 0.96
B10: 4 | C10: PC Jeweller | D10: 10.38 | E10: 8202.09 | F10: 1594.49 | G10: 0.22
B11: 55 | C11: SJ Corp | D11: 71.47 | E11: 59.71 | F11: 0 | G11: 0
B13: =B11 -> 55 | C13: =C11 -> SJ Corp | D13: =D11 -> 71.47 | E13: =E11 -> 59.71 | F13: =F11 -> 0 | G13: =G11 -> 0
B14: 41 | C14: Narbada Gems | D14: 59.25 | E14: 125.36 | F14: 28.57 | G14: 0.48
B15: 42 | C15: Moksh Ornaments | D15: 13.39 | E15: 118.17 | F15: 38.75 | G15: 0.31
B16: 57 | C16: Mishka Exim | D16: 40.9 | E16: 59.1 | F16: 1.23 | G16: 0.07
B17: 52 | C17: Bhakti Gems | D17: 43.13 | E17: 64.86 | F17: 0.81 | G17: 0.03

Sheet dccf
C8: Wegithr Average Cost Of Capital
C10: All Figure are in INR unless Stated Otherwise
C12: Peers Companies
H13: Debt/ | I13: Debt/ | J13: Levered | K13: Unlevered
C14: Name oF Company | D14: Country | E14: Total Debt | F14: Total Equity | G14: Tax Rate 1 | H14: Equity | I14: Equity | J14: Beta 2 | K14: Beta 3
C15: SJ Corp | D15: India | E15: ='comps -raw'!F13 -> 0 | F15: ='comps -raw'!E13 -> 59.71 | G15: 0.3 | H15: =IFERROR(E15/F15,0) -> 0 | I15: =IFERROR(E15/(SUM(E15:F15)),0) -> 0 | J15: ='beta sj corpoation'!L14 -> -0.1905929 | K15: =J15/(1+(1-G15)*H15) -> -0.1905929
C16: Narbada Gems | D16: India | E16: ='comps -raw'!F14 -> 28.57 | F16: ='comps -raw'!E14 -> 125.36 | G16: 0.3 | H16: =IFERROR(E16/F16,0) -> 0.22790364 | I16: =IFERROR(E16/(SUM(E16:F16)),0) -> 0.18560385 | J16: ='Narbada beta'!J21 -> 0.34097493 | K16: =J16/(1+(1-G16)*H16) -> 0.2940624
C17: Moksh Ornaments | D17: India | E17: ='comps -raw'!F15 -> 38.75 | F17: ='comps -raw'!E15 -> 118.17 | G17: 0.3 | H17: =IFERROR(E17/F17,0) -> 0.32791741 | I17: =IFERROR(E17/(SUM(E17:F17)),0) -> 0.24694112 | J17: ='Moksh BETA'!J15 -> 0.58487445 | K17: =J17/(1+(1-G17)*H17) -> 0.47568474
C18: Mishka Exim | D18: India | E18: ='comps -raw'!F16 -> 1.23 | F18: ='comps -raw'!E16 -> 59.1 | G18: 0.3 | H18: =IFERROR(E18/F18,0) -> 0.020812183 | I18: =IFERROR(E18/(SUM(E18:F18)),0) -> 0.020387867 | J18: ='Mishka Exim Ltd'!J15 -> 0.69271189 | K18: =J18/(1+(1-G18)*H18) -> 0.68276501
C19: Bhakti Gems | D19: India | E19: ='comps -raw'!F17 -> 0.81 | F19: ='comps -raw'!E17 -> 64.86 | G19: 0.3 | H19: =IFERROR(E19/F19,0) -> 0.012488437 | I19: =IFERROR(E19/(SUM(E19:F19)),0) -> 0.012334399 | J19: ='Guru BETA'!K21 -> 0.2245264 | K19: =J19/(1+(1-G19)*H19) -> 0.22258062
F22: Average | G22: =AVERAGE(G15:G19) -> 0.3 | H22: =AVERAGE(H15:H19) -> 0.11782433 | I22: =AVERAGE(I15:I19) -> 0.093053446 | J22: =AVERAGE(J15:J19) -> 0.33049895 | K22: =AVERAGE(K15:K19) -> 0.29689997
F23: Median | G23: =MEDIAN(G15:G19) -> 0.3 | H23: =MEDIAN(H15:H19) -> 0.020812183 | I23: =MEDIAN(I15:I19) -> 0.020387867 | J23: =MEDIAN(J15:J19) -> 0.34097493 | K23: =MEDIAN(K15:K19) -> 0.2940624
C27: Cost of Debt | H27: Cost Of Equity
C29: Pre-Tax Cost of Debt | F29: =IFERROR(120/E15,0) -> 0 | H29: Risk Free Rate | K29: 0.06695
C30: Tax | F30: =G16 -> 0.3 | H30: Equity Risk Premium | K30: ='market return'!U12-dccf!K29 -> 0.076354762
C31: After Tax Cost Debt | F31: =F29*(1-F30) -> 0 | H31: Levered Bta 4 | K31: =K40 -> 0.30122537
H32: Cost Of Equity | K32: =K29+K30*K31 -> 0.089949991
C35: Capital Structure | H35: Levered Beta
E37: Current | F37: Traget | H37: comps Median Unlevered Beta | K37: =K22 -> 0.29689997
C38: Total Debt | D38: =E15 -> 0 | E38: =H15 -> 0 | F38: =I23 -> 0.020387867 | H38: Traget Debt/Equity | K38: =F43 -> 0.020812183
C39: Market Capitaliziation | D39: =F15 -> 59.71 | E39: =D39/$D$40 -> 1 | F39: =F40-F38 -> 0.97961213 | H39: Tax Rate | K39: =G16 -> 0.3
C40: Total Capitalization | D40: =IFERROR(SUM(D38:D39),0) -> 59.71 | E40: =100% -> 1 | F40: =100% -> 1 | H40: levered Beta | K40: =K37*(1+(1-K39)*K38) -> 0.30122537
C43: Debt/Equity | E43: =IFERROR(E38/E39,0) -> 0 | F43: =IFERROR(F38/F39,0) -> 0.020812183 | H43: Weighted Average Cost of Capital
C45: 1. Tax Rate considered as Marginal Tax Rate for the country | H45: Cost of Equity | K45: =K32 -> 0.089949991
C46: 2. Levered Beta is based on 5 year monthly data | H46: Equity Weight | K46: =E39 -> 1
C47: 3. Unlevered Beta = Levered Beta/(1+(1-Tax Rate) x Debt/Equity)
C48: 4. Levered Beta = Unlevered Beta*(1+(1-Tax Rate) x Debt/Equity) | H48: Cost of Debt | K48: =F31 -> 0
H49: Debt Weight | K49: =F38 -> 0.020387867
H51: WACC | K51: =(K45*K46)+(K48*K49) -> 0.089949991

Sheet market return
B6: Return on market nifty 50 26 years | P6: 0.0763 | Q6: 5 YEAR AVERAGE
P7: Return on market Sensex last 21 years
B9: Year | C9: Annual | P9: 2026 | R9: -0.0224
B10: 2000 | C10: -0.1465 | E10: Average Return | G10: =AVERAGE(C10:C35) -> 0.15149231 | H10: =MEDIAN(C10:C35) -> 0.1135 | P10: 2025 | R10: 0.0906 | T10: Average return | U10: =AVERAGE(R9:R29) -> 0.14330476
B11: 2001 | C11: -0.1618 | E11: Dividevd yield | G11: 1.39% 1 | P11: 2024 | R11: 0.0817 | T11: Dividevd yield | U11: 1.15 1
B12: 2002 | C12: 0.0325 | E12: Total Market Return | G12: =SUM(G10:G11) -> 0.15149231 | P12: 2023 | R12: 0.1874 | T12: Total Market Return | U12: =SUM(U10:U11) -> 0.14330476
B13: 2003 | C13: 0.719 | P13: 2022 | R13: 0.0444
B14: 2004 | C14: 0.1068 | P14: 2021 | R14: 0.2199
B15: 2005 | C15: 0.3634 | P15: 2020 | R15: 0.1575
B16: 2006 | C16: 0.3983 | P16: 2019 | R16: 0.1438
B17: 2007 | C17: 0.5477 | P17: 2018 | R17: 0.0591
B18: 2008 | C18: -0.5179 | P18: 2017 | R18: 0.2791
B19: 2009 | C19: 0.7576 | P19: 2016 | R19: 0.0195
B20: 2010 | C20: 0.1795 | P20: 2015 | R20: -0.0503
B21: 2011 | C21: -0.2462 | P21: 2014 | R21: 0.2989
B22: 2012 | C22: 0.277 | P22: 2013 | R22: 0.0898
B23: 2013 | C23: 0.0676 | P23: 2012 | R23: 0.257
B24: 2014 | C24: 0.3139 | P24: 2011 | R24: -0.2464
... B29: 2019 | C29: 0.1202 | P29: 2006 | R29: 0.4682
B30: 2020 | C30: 0.149
B31: 2021 | C31: 0.2412
B32: 2022 | C32: 0.0432
B33: 2023 | C33: 0.1942
B34: 2024 | C34: 0.0875
B35: 2025 | C35: 0.1051

Sheet sp j corporation
B2: Date | C2: Adj Close | D2: Close | E2: Volume | F2: Close | G2: Date | H2: Adj Close | I2: Volume | J2: Close | M2: Date | N2: Adj Close | O2: Volume | P2: Open | Q2: High | R2: Low | S2: Close
B3: Jan 26 2026 | C3: 68.07 | D3: 6807 | E3: 1525 | F3: 6807 | G3: Jan 26 2026 | H3: 8226978 | I3: 97600 | J3: 8226978 | M3: 46048 | N3: 68.07 | O3: 1525 | P3: 65 | Q3: 68.07 | R3: 61.75 | S3: 68.07 | V3: Date
B4: Jan 19 2026 | C4: 65 | D4: 6500 | E4: - | F4: 6500 | G4: Jan 19 2026 | H4: 8153770 | I4: 86600 | J4: 8153770 | M4: 46041 | N4: 65 | O4: - | P4: 65 | Q4: 65 | R4: 65 | S4: 65
B5: Jan 12 2026 | C5: 65 | D5: 6500 | E5: - | F5: 6500 | G5: Jan 12 2026 | H5: 8357035 | I5: 60400 | J5: 8357035 | M5: 46034 | N5: 65 | O5: - | P5: 65 | Q5: 65 | R5: 65 | S5: 65 | V5: Price
B6: Jan 5 2026 | C6: 65 | D6: 6500 | E6: - | F6: 6500 | G6: Jan 5 2026 | H6: 8357624 | I6: 93900 | J6: 8357624 | M6: 46027 | N6: 65 | O6: - | P6: 65 | Q6: 65 | R6: 65 | S6: 65
B7: Dec 29 2025 | C7: 65 | D7: 6500 | E7: 150 | F7: 6500 | G7: Dec 29 2025 | H7: 8576201 | I7: 110300 | J7: 8576201 | M7: 46020 | N7: 65 | O7: 150 | P7: 65 | Q7: 65 | R7: 65 | S7: 65 | V7: Open
B8: Dec 22 2025 | C8: 65 | D8: 6500 | E8: - | F8: 6500 | G8: Dec 22 2025 | H8: 8504145 | I8: 25400 | J8: 8504145 | M8: 46013 | N8: 65 | O8: - | P8: 65 | Q8: 65 | R8: 65 | S8: 65
B9: Dec 15 2025 | C9: 65 | D9: 6500 | E9: - | F9: 6500 | G9: Dec 15 2025 | H9: 8492936 | I9: 54500 | J9: 8492936 | M9: 46006 | N9: 65 | O9: - | P9: 65 | Q9: 65 | R9: 65 | S9: 65 | V9: High
B10: Dec 8 2025 | C10: 65 | D10: 6500 | E10: - | F10: 6500 | G10: Dec 8 2025 | H10: 8526766 | I10: 52000 | J10: 8526766 | M10: 45999 | N10: 65 | O10: - | P10: 65 | Q10: 65 | R10: 65 | S10: 65
B11: Dec 1 2025 | C11: 65 | D11: 6500 | E11: - | F11: 6500 | G11: Dec 1 2025 | H11: 8571237 | I11: 57500 | J11: 8571237 | M11: 45992 | N11: 65 | O11: - | P11: 65 | Q11: 65 | R11: 65 | S11: 65 | V11: Low
B12: Nov 24 2025 | C12: 65 | D12: 6500 | E12: - | F12: 6500 | G12: Nov 24 2025 | H12: 8570667 | I12: 51800 | J12: 8570667 | M12: 45985 | N12: 65 | O12: - | P12: 65 | Q12: 65 | R12: 65 | S12: 65
B13: Nov 17 2025 | C13: 65 | D13: 6500 | E13: - | F13: 6500 | G13: Nov 17 2025 | H13: 8523192 | I13: 68600 | J13: 8523192 | M13: 45978 | N13: 65 | O13: - | P13: 65 | Q13: 65 | R13: 65 | S13: 65 | V13: Vol.
B14: Nov 10 2025 | C14: 65 | D14: 6500 | E14: - | F14: 6500 | G14: Nov 10 2025 | H14: 8456278 | I14: 71900 | J14: 8456278 | M14: 45971 | N14: 65 | O14: - | P14: 65 | Q14: 65 | R14: 65 | S14: 65
B15: Nov 3 2025 | C15: 65 | D15: 6500 | E15: - | F15: 6500 | G15: Nov 3 2025 | H15: 8321628 | I15: 44600 | J15: 8321628 | M15: 45964 | N15: 65 | O15: - | P15: 65 | Q15: 65 | R15: 65 | S15: 65 | V15: High | W15: =V5 -> Price | X15: Open | Y15: High | Z15: Low | AA15: =AA3 -> 0
B16: Oct 27 2025 | C16: 65 | D16: 6500 | E16: - | F16: 6500 | G16: Oct 27 2025 | H16: 8393871 | I16: 66000 | J16: 8393871 | M16: 45957 | N16: 65 | O16: - | P16: 65 | Q16: 65 | R16: 65 | S16: 65 | V16: 46024 | W16: 58.09 | X16: 55.62 | Y16: 60.2 | Z16: 55.62 | AA16: 6.62K | AB16: 0.0236
B17: Oct 20 2025 | C17: 65 | D17: 6500 | E17: 188 | F17: 6500 | G17: Oct 20 2025 | H17: 8421188 | I17: 53600 | J17: 8421188 | M17: 45950 | N17: 65 | O17: 188 | P17: 65.61 | Q17: 65.61 | R17: 65 | S17: 65 | V17: 25-01-2026 | W17: 56.75 | X17: 58.49 | Y17: 62.98 | Z17: 55.17 | AA17: 4.99K | AB17: -0.0249
B18: Oct 13 2025 | C18: 64.97 | D18: 6497 | E18: - | F18: 6497 | G18: Oct 13 2025 | H18: 8395219 | I18: 73900 | J18: 8395219 | M18: 45943 | N18: 64.97 | O18: - | P18: 64.97 | Q18: 64.97 | R18: 64.97 | S18: 64.97 | V18: 18-01-2026 | W18: 58.2 | X18: 61 | Y18: 63 | Z18: 56.1 | AA18: 4.78K | AB18: -0.0889
B19: Oct 6 2025 | C19: 64.97 | D19: 6497 | E19: - | F19: 6497 | G19: Oct 6 2025 | H19: 8250082 | I19: 74800 | J19: 8250082 | M19: 45936 | N19: 64.97 | O19: - | P19: 64.97 | Q19: 64.97 | R19: 64.97 | S19: 64.97 | V19: 46327 | W19: 63.88 | X19: 64.18 | Y19: 64.5 | Z19: 59.23 | AA19: 4.48K | AB19: -0.0047
B20: Sep 29 2025 | C20: 64.97 | D20: 6497 | E20: - | F20: 6497 | G20: Sep 29 2025 | H20: 8120717 | I20: 51600 | J20: 8120717 | M20: 45929 | N20: 64.97 | O20: - | P20: 64.97 | Q20: 64.97 | R20: 64.97 | S20: 64.97 | V20: 46113 | W20: 64.18 | X20: 65.7 | Y20: 69.5 | Z20: 61 | AA20: 12.01K | AB20: 0.0134
B21: Sep 22 2025 | C21: 64.97 | D21: 6497 | E21: - | F21: 6497 | G21: Sep 22 2025 | H21: 8042646 | I21: 60200 | J21: 8042646 | M21: 45922 | N21: 64.97 | O21: - | P21: 64.97 | Q21: 64.97 | R21: 64.97 | S21: 64.97 | V21: 28-12-2025 | W21: 63.33 | X21: 67 | Y21: 67 | Z21: 57 | AA21: 4.86K | AB21: -0.0861
B22: Sep 15 2025 | C22: 64.97 | D22: 6497 | E22: - | F22: 6497 | G22: Sep 15 2025 | H22: 8262623 | I22: 57600 | J22: 8262623 | M22: 45915 | N22: 64.97 | O22: - | P22: 64.97 | Q22: 64.97 | R22: 64.97 | S22: 64.97 | V22: 21-12-2025 | W22: 69.3 | X22: 64.98 | Y22: 69.5 | Z22: 59.72 | AA22: 0.67K | AB22: 0.0869
B23: Sep 8 2025 | C23: 64.97 | D23: 6497 | E23: - | F23: 6497 | G23: Sep 8 2025 | H23: 8190470 | I23: 51400 | J23: 8190470 | M23: 45908 | N23: 64.97 | O23: - | P23: 64.97 | Q23: 64.97 | R23: 64.97 | S23: 64.97 | V23: 14-12-2025 | W23: 63.76 | X23: 65.01 | Y23: 70 | Z23: 57.2 | AA23: 4.38K | AB23: -0.0558
B24: Sep 1 2025 | C24: 64.97 | D24: 6497 | E24: - | F24: 6497 | G24: Sep 1 2025 | H24: 8071076 | I24: 56500 | J24: 8071076 | M24: 45901 | N24: 64.97 | O24: - | P24: 64.97 | Q24: 64.97 | R24: 64.97 | S24: 64.97 | V24: 45850 | W24: 67.53 | X24: 69.39 | Y24: 70.5 | Z24: 64.3 | AA24: 0.57K | AB24: -0.0268
B25: Aug 25 2025 | C25: 64.97 | D25: 6497 | E25: 1 | F25: 6497 | G25: Aug 25 2025 | H25: 7980965 | I25: 50500 | J25: 7980965 | M25: 45894 | N25: 64.97 | O25: 1 | P25: 64.97 | Q25: 64.97 | R25: 64.97 | S25: 64.97 | V25: 30-11-2025 | W25: 69.39 | X25: 73.98 | Y25: 73.98 | Z25: 65.35 | AA25: 1.77K | AB25: 0.0114
B26: Aug 18 2025 | C26: 58.94 | D26: 5894 | E26: - | F26: 5894 | G26: Aug 18 2025 | H26: 8130685 | I26: 56400 | J26: 8130685 | M26: 45887 | N26: 58.94 | O26: - | P26: 58.94 | Q26: 58.94 | R26: 58.94 | S26: 58.94 | V26: 23-11-2025 | W26: 68.61 | X26: 66 | Y26: 69.4 | Z26: 66 | AA26: 6.69K | AB26: -0.0055 | AE26: sensex x inest doc, com
B27: Aug 11 2025 | C27: 58.94 | D27: 5894 | E27: - | F27: 5894 | G27: Aug 11 2025 | H27: 8059766 | I27: 38400 | J27: 8059766 | M27: 45880 | N27: 58.94 | O27: - | P27: 58.94 | Q27: 58.94 | R27: 58.94 | S27: 58.94 | V27: 16-11-2025 | W27: 68.99 | X27: 74 | Y27: 77 | Z27: 68.5 | AA27: 14.05K | AB27: -0.0589
B28: Aug 4 2025 | C28: 58.94 | D28: 5894 | E28: - | F28: 5894 | G28: Aug 4 2025 | H28: 7985779 | I28: 86800 | J28: 7985779 | M28: 45873 | N28: 58.94 | O28: - | P28: 58.94 | Q28: 58.94 | R28: 58.94 | S28: 58.94 | V28: 45911 | W28: 73.31 | X28: 70.46 | Y28: 75 | Z28: 67.51 | AA28: 10.18K | AB28: 0.0615
B29: Jul 28 2025 | C29: 58.94 | D29: 5894 | E29: - | F29: 5894 | G29: Jul 28 2025 | H29: 8059991 | I29: 49000 | J29: 8059991 | M29: 45866 | N29: 58.94 | O29: - | P29: 58.94 | Q29: 58.94 | R29: 58.94 | S29: 58.94 | V29: 45699 | W29: 69.06 | X29: 70.05 | Y29: 74.9 | Z29: 66.52 | AA29: 11.22K | AB29: -0.0537 | AE29: Date | AF29: Price | AG29: Price | AH29: Price | AI29: Price
B30: Jul 21 2025 | C30: 58.94 | D30: 5894 | E30: - | F30: 5894 | G30: Jul 21 2025 | H30: 8146309 | I30: 73300 | J30: 8146309 | M30: 45859 | N30: 58.94 | O30: - | P30: 58.94 | Q30: 58.94 | R30: 58.94 | S30: 58.94 | V30: 26-10-2025 | W30: 72.98 | X30: 75 | Y30: 77 | Z30: 68.4 | AA30: 10.08K | AB30: 0.0039 | AE30: 46024 | AF30: 83817.69 | AG30: 82388.97 | AH30: 85871.73 | AI30: 79899.42 | AJ30: 72.45M | AK30: 0.0188 | AM30: Date | AO30: Open | AP30: High | AQ30: Low | AV30: Open | AW30: High | AX30: Low | BD30: Open | BE30: High | BF30: Low
B31: Jul 14 2025 | C31: 58.94 | D31: 5894 | E31: 20 | F31: 5894 | G31: Jul 14 2025 | H31: 8175773 | I31: 52700 | J31: 8175773 | M31: 45852 | N31: 58.94 | O31: 20 | P31: 56.14 | Q31: 58.94 | R31: 56.14 | S31: 58.94 | V31: 19-10-2025 | W31: 72.7 | X31: 69.95 | Y31: 75.8 | Z31: 68 | AA31: 4.71K | AB31: 0.0393 | AE31: 25-01-2026 | AF31: 82269.78 | AG31: 81436.79 | AH31: 82689.96 | AI31: 81088.59 | AJ31: 97.65M | AK31: 0.009 | AM31: 46024 | AN31: 13.39 | AO31: 13.41 | AP31: 14.3 | AQ31: 13 | AR31: 440.62K | AS31: -0.0262 | AU31: 46024 | AV31: 40.9 | AW31: 41.51 | AX31: 43.15 | AY31: 40.9 | AZ31: 14.46K | BA31: 0.0049 | BC31: 46024 | BD31: 43.13 | BE31: 41.2 | BF31: 44.98 | BG31: 39.5 | BH31: 419.09K | BI31: 0.0403
B32: Jul 7 2025 | C32: 56.14 | D32: 5614 | E32: - | F32: 5614 | G32: Jul 7 2025 | H32: 8250047 | I32: 47500 | J32: 8250047 | M32: 45845 | N32: 56.14 | O32: - | P32: 56.14 | Q32: 56.14 | R32: 56.14 | S32: 56.14 | V32: 46001 | W32: 69.95 | X32: 72.41 | Y32: 72.41 | Z32: 67.5 | AA32: 12.38K | AB32: -0.0388 | AE32: 18-01-2026 | AF32: 81537.7 | AG32: 83494.49 | AH32: 83539.93 | AI32: 81124.45 | AJ32: 86.59M | AK32: -0.0243 | AM32: 25-01-2026 | AN32: 13.75 | AO32: 14.15 | AP32: 14.49 | AQ32: 13.51 | AR32: 572.54K | AS32: -0.0337 | AU32: 25-01-2026 | AV32: 40.7 | AW32: 43.95 | AX32: 44.2 | AY32: 40.1 | AZ32: 8.28K | BA32: -0.0739 | BC32: 25-01-2026 | BD32: 41.46 | BE32: 44.49 | BF32: 44.49 | BG32: 40 | BH32: 273.48K | BI32: -0.0473
B33: Jun 30 2025 | C33: 56.14 | D33: 5614 | E33: - | F33: 5614 | G33: Jun 30 2025 | H33: 8343289 | I33: 54300 | J33: 8343289 | M33: 45838 | N33: 56.14 | O33: - | P33: 56.14 | Q33: 56.14 | R33: 56.14 | S33: 56.14 | V33: 45787 | W33: 72.77 | X33: 71 | Y33: 77 | Z33: 66.54 | AA33: 20.12K | AB33: 0.0452 | AE33: 46327 | AF33: 83570.35 | AG33: 83435.31 | AH33: 84258.03 | AI33: 82861.07 | AJ33: 60.42M | AK33: -0.0001 | AM33: 18-01-2026 | AN33: 14.23 | AO33: 14.58 | AP33: 14.98 | AQ33: 13.8 | AR33: 442.16K | AS33: -0.0353 | AU33: 18-01-2026 | AV33: 43.95 | AW33: 44.2 | AX33: 46.49 | AY33: 42 | AZ33: 18.57K | BA33: -0.0057 | BC33: 18-01-2026 | BD33: 43.52 | BE33: 44.4 | BF33: 45 | BG33: 40.83 | BH33: 735.51K | BI33: 0.0152
B34: Jun 23 2025 | C34: 56.14 | D34: 5614 | E34: - | F34: 5614 | G34: Jun 23 2025 | H34: 8405890 | I34: 153900 | J34: 8405890 | M34: 45831 | N34: 56.14 | O34: - | P34: 56.14 | Q34: 56.14 | R34: 56.14 | S34: 56.14 | V34: 28-09-2025 | W34: 69.62 | X34: 64.15 | Y34: 70.45 | Z34: 64.15 | AA34: 6.09K | AB34: 0.0051 | AE34: 46113 | AF34: 83576.24 | AG34: 85640.05 | AH34: 85883.5 | AI34: 83402.28 | AJ34: 93.88M | AK34: -0.0255 | AM34: 46327 | AN34: 14.75 | AO34: 15 | AP34: 15.4 | AQ34: 14.6 | AR34: 284.39K | AS34: -0.018 | AU34: 46327 | AV34: 44.2 | AW34: 40.1 | AX34: 44.21 | AY34: 40 | AZ34: 20.68K | BA34: 0.105 | BC34: 46327 | BD34: 42.87 | BE34: 44.25 | BF34: 49.49 | BG34: 42.85 | BH34: 1.97M | BI34: -0.0277
B35: Jun 16 2025 | C35: 56.14 | D35: 5614 | E35: - | F35: 5614 | G35: Jun 16 2025 | H35: 8240817 | I35: 63400 | J35: 8240817 | M35: 45824 | N35: 56.14 | O35: - | P35: 56.14 | Q35: 56.14 | R35: 56.14 | S35: 56.14 | V35: 21-09-2025 | W35: 69.27 | X35: 70.5 | Y35: 73.44 | Z35: 66 | AA35: 19.24K | AB35: -0.0114 | AE35: 28-12-2025 | AF35: 85762.01 | AG35: 85004.75 | AH35: 85812.27 | AI35: 84470.94 | AJ35: 110.34M | AK35: 0.0085 | AM35: 46113 | AN35: 15.02 | AO35: 14.15 | AP35: 16.39 | AQ35: 14.15 | AR35: 2.40M | AS35: 0.0351 | AU35: 46113 | AV35: 40 | AW35: 41 | AX35: 43.59 | AY35: 39.01 | AZ35: 17.85K | BA35: -0.0419 | BC35: 46113 | BD35: 44.09 | BE35: 37.03 | BF35: 44.75 | BG35: 36.8 | BH35: 1.75M | BI35: 0.1881
B36: Jun 9 2025 | C36: 56.14 | D36: 5614 | E36: 100 | F36: 5614 | G36: Jun 9 2025 | H36: 8111860 | I36: 50500 | J36: 8111860 | M36: 45817 | N36: 56.14 | O36: 100 | P36: 56.14 | Q36: 56.14 | R36: 56.14 | S36: 56.14 | V36: 14-09-2025 | W36: 70.07 | X36: 72 | Y36: 76 | Z36: 66.5 | AA36: 16.79K | AB36: -0.0253 | AE36: 21-12-2025 | AF36: 85041.45 | AG36: 85145.9 | AH36: 85738.18 | AI36: 84937.82 | AJ36: 25.47M | AK36: 0.0013 | AM36: 28-12-2025 | AN36: 14.51 | AO36: 15 | AP36: 15.6 | AQ36: 13.98 | AR36: 1.28M | AS36: -0.0365 | AU36: 28-12-2025 | AV36: 41.75 | AW36: 40.5 | AX36: 42.5 | AY36: 39.1 | AZ36: 14.86K | BA36: 0.0427 | BC36: 28-12-2025 | BD36: 37.11 | BE36: 36.6 | BF36: 37.74 | BG36: 34.01 | BH36: 927.76K | BI36: 0.0139
B37: Jun 2 2025 | C37: 53.47 | D37: 5347 | E37: - | F37: 5347 | G37: Jun 2 2025 | H37: 8218899 | I37: 71600 | J37: 8218899 | M37: 45810 | N37: 53.47 | O37: - | P37: 53.47 | Q37: 53.47 | R37: 53.47 | S37: 53.47 | V37: 45847 | W37: 71.89 | X37: 63.25 | Y37: 72.4 | Z37: 63.25 | AA37: 11.48K | AB37: -0.0024 | AE37: 14-12-2025 | AF37: 84929.36 | AG37: 84891.75 | AH37: 85278.63 | AI37: 84238.43 | AJ37: 55.51M | AK37: -0.004 | AM37: 21-12-2025 | AN37: 15.06 | AO37: 15.31 | AP37: 15.75 | AQ37: 14.91 | AR37: 514.36K | AS37: -0.017 | AU37: 21-12-2025 | AV37: 40.04 | AW37: 46.7 | AX37: 46.7 | AY37: 40.02 | AZ37: 12.67K | BA37: -0.1 | BC37: 21-12-2025 | BD37: 36.6 | BE37: 32.28 | BF37: 38.97 | BG37: 32 | BH37: 1.50M | BI37: 0.137
B38: May 26 2025 | C38: 53.47 | D38: 5347 | E38: - | F38: 5347 | G38: May 26 2025 | H38: 8145101 | I38: 74400 | J38: 8145101 | M38: 45803 | N38: 53.47 | O38: - | P38: 53.47 | Q38: 53.47 | R38: 53.47 | S38: 53.47 | V38: 31-08-2025 | W38: 72.06 | X38: 68.36 | Y38: 75 | Z38: 63 | AA38: 29.92K | AB38: 0.0277 | AE38: 45850 | AF38: 85267.66 | AG38: 85624.84 | AH38: 85722.97 | AI38: 84150.19 | AJ38: 51.94M | AK38: -0.0052 | AM38: 14-12-2025 | AN38: 15.32 | AO38: 13.85 | AP38: 16.65 | AQ38: 13.85 | AR38: 1.82M | AS38: 0.0888 | AU38: 14-12-2025 | AV38: 44.49 | AW38: 45.03 | AX38: 45.03 | AY38: 42.75 | AZ38: 20.03K | BA38: -0.0116 | BC38: 14-12-2025 | BD38: 32.19 | BE38: 28.57 | BF38: 32.31 | BG38: 27.65 | BH38: 1.33M | BI38: 0.1323
B39: May 19 2025 | C39: 53.47 | D39: 5347 | E39: - | F39: 5347 | G39: May 19 2025 | H39: 8172108 | I39: 47100 | J39: 8172108 | M39: 45796 | N39: 53.47 | O39: - | P39: 53.47 | Q39: 53.47 | R39: 53.47 | S39: 53.47 | V39: 24-08-2025 | W39: 70.12 | X39: 73.59 | Y39: 73.59 | Z39: 64.25 | AA39: 26.69K | AB39: -0.0472 | AE39: 30-11-2025 | AF39: 85712.37 | AG39: 86065.92 | AH39: 86159.02 | AI39: 84763.64 | AJ39: 57.49M | AK39: 0.0001 | AM39: 45850 | AN39: 14.07 | AO39: 14.36 | AP39: 14.56 | AQ39: 13.75 | AR39: 357.21K | AS39: -0.0303 | AU39: 45850 | AV39: 45.01 | AW39: 45.05 | AX39: 46.59 | AY39: 44.99 | AZ39: 8.83K | BA39: -0.0421 | BC39: 45850 | BD39: 28.43 | BE39: 30 | BF39: 30 | BG39: 27.2 | BH39: 1.33M | BI39: -0.0183
B40: May 12 2025 | C40: 53.47 | D40: 5347 | E40: 290 | F40: 5347 | G40: May 12 2025 | H40: 8233059 | I40: 70000 | J40: 8233059 | M40: 45789 | N40: 53.47 | O40: 53.47 | P40: 53.47 | Q40: 53.47 | R40: 53.47 | S40: 290 | V40: 17-08-2025 | W40: 73.59 | X40: 58.68 | Y40: 75.99 | Z40: 57.7 | AA40: 122.67K | AB40: 0.338 | AE40: 23-11-2025 | AF40: 85706.67 | AG40: 85320.04 | AH40: 86055.86 | AI40: 84478.13 | AJ40: 51.86M | AK40: 0.0056 | AM40: 30-11-2025 | AN40: 14.51 | AO40: 14.35 | AP40: 15.01 | AQ40: 14.02 | AR40: 2.19M | AS40: 0 | AU40: 30-11-2025 | AV40: 46.99 | AW40: 48 | AX40: 48 | AY40: 44.51 | AZ40: 13.83K | BA40: 0.0019 | BC40: 30-11-2025 | BD40: 28.96 | BE40: 27.5 | BF40: 30 | BG40: 26.93 | BH40: 1.61M | BI40: 0.0523
B41: May 5 2025 | C41: 53.47 | D41: 5347 | E41: - | F41: 5347 | G41: May 5 2025 | H41: 7945447 | I41: 49500 | J41: 7945447 | M41: 45782 | N41: 53.47 | O41: 53.47 | P41: 53.47 | Q41: 53.47 | R41: 53.47 | S41: - | V41: 45938 | W41: 55 | X41: 52.7 | Y41: 56.9 | Z41: 51.26 | AA41: 24.47K | AB41: 0.0427 | AE41: 16-11-2025 | AF41: 85231.92 | AG41: 84700.5 | AH41: 85801.7 | AI41: 84525.98 | AJ41: 68.47M | AK41: 0.0079 | AM41: 23-11-2025 | AN41: 14.51 | AO41: 13.45 | AP41: 15.35 | AQ41: 13.45 | AR41: 6.65M | AS41: 0.0951 | AU41: 23-11-2025 | AV41: 46.9 | AW41: 48 | AX41: 48 | AY41: 44.5 | AZ41: 11.20K | BA41: 0.0017 | BC41: 23-11-2025 | BD41: 27.52 | BE41: 26.59 | BF41: 27.53 | BG41: 25.81 | BH41: 471.22K | BI41: 0.0508
B42: Apr 28 2025 | C42: 53.47 | D42: 5347 | E42: - | F42: 5347 | G42: Apr 28 2025 | H42: 8050199 | I42: 49600 | J42: 8050199 | M42: 45775 | N42: 53.47 | O42: 53.47 | P42: 53.47 | Q42: 53.47 | R42: 53.47 | S42: - | V42: 45724 | W42: 52.75 | X42: 53.9 | Y42: 53.9 | Z42: 50 | AA42: 5.45K | AB42: 0.0487 | AE42: 45911 | AF42: 84562.78 | AG42: 83198.2 | AH42: 84919.43 | AI42: 83124.03 | AJ42: 71.95M | AK42: 0.0162 | AM42: 16-11-2025 | AN42: 13.25 | AO42: 15.17 | AP42: 15.7 | AQ42: 11.56 | AR42: 4.12M | AS42: -0.1266 | AU42: 16-11-2025 | AV42: 46.82 | AW42: 45.3 | AX42: 48 | AY42: 43 | AZ42: 27.51K | BA42: 0.0432 | BC42: 16-11-2025 | BD42: 26.19 | BE42: 25.3 | BF42: 26.95 | BG42: 25.3 | BH42: 728.66K | BI42: 0.0291
B43: Apr 21 2025 | C43: 53.47 | D43: 5347 | E43: - | F43: 5347 | G43: Apr 21 2025 | H43: 7921253 | I43: 60800 | J43: 7921253 | M43: 45768 | N43: 53.47 | O43: 53.47 | P43: 53.47 | Q43: 53.47 | R43: 53.47 | S43: - | V43: 27-07-2025 | W43: 50.3 | X43: 50.96 | Y43: 52.45 | Z43: 50 | AA43: 23.28K | AB43: 0.0046 | AE43: 45699 | AF43: 83216.28 | AG43: 83835.1 | AH43: 84127 | AI43: 82670.95 | AJ43: 44.72M | AK43: -0.0086 | AM43: 45911 | AN43: 15.17 | AO43: 14.48 | AP43: 15.49 | AQ43: 14.05 | AR43: 3.56M | AS43: 0.0623 | AU43: 45911 | AV43: 44.88 | AW43: 45 | AX43: 48.78 | AY43: 42.18 | AZ43: 58.00K | BA43: -0.0423 | BC43: 45911 | BD43: 25.45 | BE43: 25 | BF43: 25.85 | BG43: 24.22 | BH43: 547.59K | BI43: 0.0213
B44: Apr 14 2025 | C44: 53.47 | D44: 5347 | E44: - | F44: 5347 | G44: Apr 14 2025 | H44: 7855320 | I44: 33500 | J44: 7855320 | M44: 45761 | N44: 53.47 | O44: 53.47 | P44: 53.47 | Q44: 53.47 | R44: 53.47 | S44: - | V44: 20-07-2025 | W44: 50.07 | X44: 51.5 | Y44: 51.5 | Z44: 49.5 | AA44: 5.52K | AB44: -0.0211 | AE44: 26-10-2025 | AF44: 83938.71 | AG44: 84297.39 | AH44: 85105.83 | AI44: 83905.66 | AJ44: 65.93M | AK44: -0.0032 | AM44: 45699 | AN44: 14.28 | AO44: 14.18 | AP44: 14.45 | AQ44: 13.76 | AR44: 1.34M | AS44: 0.0273 | AU44: 45699 | AV44: 46.86 | AW44: 38.56 | AX44: 48.69 | AY44: 38.5 | AZ44: 70.60K | BA44: 0.2152 | BC44: 45699 | BD44: 24.92 | BE44: 24.25 | BF44: 26 | BG44: 23.45 | BH44: 344.59K | BI44: 0.0396
B45: Apr 7 2025 | C45: 53.47 | D45: 5347 | E45: - | F45: 5347 | G45: Apr 7 2025 | H45: 7515726 | I45: 69800 | J45: 7515726 | M45: 45754 | N45: 53.47 | O45: 53.47 | P45: 53.47 | Q45: 53.47 | R45: 53.47 | S45: - | V45: 13-07-2025 | W45: 51.15 | X45: 53.48 | Y45: 54.36 | Z45: 50.02 | AA45: 34.33K | AB45: -0.0439 | AE45: 19-10-2025 | AF45: 84211.88 | AG45: 84269.3 | AH45: 85290.06 | AI45: 83957.15 | AJ45: 53.62M | AK45: 0.0031 | AM45: 26-10-2025 | AN45: 13.9 | AO45: 14.22 | AP45: 14.45 | AQ45: 13.85 | AR45: 632.04K | AS45: -0.0246 | AU45: 26-10-2025 | AV45: 38.56 | AW45: 37.46 | AX45: 39 | AY45: 34.5 | AZ45: 11.20K | BA45: 0.0396 | BC45: 26-10-2025 | BD45: 23.97 | BE45: 23.36 | BF45: 24.19 | BG45: 22.35 | BH45: 516.47K | BI45: 0.0213
B46: Mar 31 2025 | C46: 53.47 | D46: 5347 | E46: - | F46: 5347 | G46: Mar 31 2025 | H46: 7536469 | I46: 40000 | J46: 7536469 | M46: 45747 | N46: 53.47 | O46: 53.47 | P46: 53.47 | Q46: 53.47 | R46: 53.47 | S46: - | V46: 45815 | W46: 53.5 | X46: 54.68 | Y46: 54.9 | Z46: 52.01 | AA46: 11.93K | AB46: -0.005 | AE46: 46001 | AF46: 83952.19 | AG46: 82049.16 | AH46: 84172.24 | AI46: 81781.62 | AJ46: 74.00M | AK46: 0.0176 | AM46: 19-10-2025 | AN46: 14.25 | AO46: 14.1 | AP46: 14.8 | AQ46: 14 | AR46: 386.15K | AS46: -0.0035 | AU46: 19-10-2025 | AV46: 37.09 | AW46: 36.64 | AX46: 38.85 | AY46: 36.34 | AZ46: 7.25K | BA46: 0.0123 | BC46: 19-10-2025 | BD46: 23.47 | BE46: 20.66 | BF46: 24.05 | BG46: 20.66 | BH46: 723.89K | BI46: 0.0796
B47: Mar 24 2025 | C47: 53.47 | D47: 5347 | E47: - | F47: 5347 | G47: Mar 24 2025 | H47: 7741492 | I47: 62700 | J47: 7741492 | M47: 45740 | N47: 53.47 | O47: 53.47 | P47: 53.47 | Q47: 53.47 | R47: 53.47 | S47: - | V47: 29-06-2025 | W47: 53.77 | X47: 54 | Y47: 55.49 | Z47: 52.21 | AA47: 9.69K | AB47: -0.0206 | AE47: 45787 | AF47: 82500.82 | AG47: 81274.79 | AH47: 82654.11 | AI47: 81155.88 | AJ47: 74.79M | AK47: 0.0159 | AM47: 46001 | AN47: 14.3 | AO47: 15.14 | AP47: 15.15 | AQ47: 14.2 | AR47: 554.62K | AS47: -0.0555 | AU47: 46001 | AV47: 36.64 | AW47: 37 | AX47: 37.18 | AY47: 35 | AZ47: 22.55K | BA47: 0.0178 | BC47: 46001 | BD47: 21.74 | BE47: 19.31 | BF47: 21.74 | BG47: 19.31 | BH47: 266.80K | BI47: 0.0725
B48: Mar 17 2025 | C48: 53.47 | D48: 5347 | E48: - | F48: 5347 | G48: Mar 17 2025 | H48: 7690551 | I48: 51700 | J48: 7690551 | M48: 45733 | N48: 53.47 | O48: 53.47 | P48: 53.47 | Q48: 53.47 | R48: 53.47 | S48: - | V48: 22-06-2025 | W48: 54.9 | X48: 54.95 | Y48: 57 | Z48: 52.5 | AA48: 5.21K | AB48: -0.0009 | AE48: 28-09-2025 | AF48: 81207.17 | AG48: 80588.77 | AH48: 81251.99 | AI48: 80159.9 | AJ48: 51.54M | AK48: 0.0097 | AM48: 45787 | AN48: 15.14 | AO48: 15.35 | AP48: 15.68 | AQ48: 14.7 | AR48: 987.61K | AS48: 0.0114 | AU48: 45787 | AV48: 36 | AW48: 35.9 | AX48: 37.58 | AY48: 33.3 | AZ48: 18.05K | BA48: 0.0286 | BC48: 45787 | BD48: 20.27 | BE48: 21 | BF48: 21.47 | BG48: 19.63 | BH48: 99.77K | BI48: -0.0283
B49: Mar 10 2025 | C49: 53.47 | D49: 5347 | E49: - | F49: 5347 | G49: Mar 10 2025 | H49: 7382891 | I49: 42000 | J49: 7382891 | M49: 45726 | N49: 53.47 | O49: 53.47 | P49: 53.47 | Q49: 53.47 | R49: 53.47 | S49: - | V49: 15-06-2025 | W49: 54.95 | X49: 56.7 | Y49: 56.7 | Z49: 53 | AA49: 3.98K | AB49: 0.0027 | AE49: 21-09-2025 | AF49: 80426.46 | AG49: 82151.07 | AH49: 82583.16 | AI49: 80332.41 | AJ49: 60.21M | AK49: -0.0266 | AM49: 28-09-2025 | AN49: 14.97 | AO49: 14.1 | AP49: 15.49 | AQ49: 13.85 | AR49: 2.08M | AS49: 0.0617 | AU49: 28-09-2025 | AV49: 35 | AW49: 34.52 | AX49: 35.96 | AY49: 32.9 | AZ49: 9.74K | BA49: -0.0339 | BC49: 28-09-2025 | BD49: 20.86 | BE49: 20.45 | BF49: 21.5 | BG49: 19.2 | BH49: 101.99K | BI49: 0.0665
B50: Mar 3 2025 | C50: 53.47 | D50: 5347 | E50: 370 | F50: 5347 | G50: Mar 3 2025 | H50: 7433258 | I50: 42600 | J50: 7433258 | M50: 45719 | N50: 53.47 | O50: 53.47 | P50: 53.47 | Q50: 53.47 | R50: 53.47 | S50: 370 | V50: 45875 | W50: 54.8 | X50: 53.5 | Y50: 55.85 | Z50: 49.3 | AA50: 26.85K | AB50: 0.0402 | AE50: 14-09-2025 | AF50: 82626.23 | AG50: 81925.51 | AH50: 83141.21 | AI50: 81744.7 | AJ50: 57.66M | AK50: 0.0088 | AM50: 21-09-2025 | AN50: 14.1 | AO50: 14.9 | AP50: 15.1 | AQ50: 14 | AR50: 1.33M | AS50: -0.0473 | AU50: 21-09-2025 | AV50: 36.23 | AW50: 38 | AX50: 38.1 | AY50: 36.05 | AZ50: 10.88K | BA50: -0.0466 | BC50: 21-09-2025 | BD50: 19.56 | BE50: 21.49 | BF50: 21.49 | BG50: 19.44 | BH50: 488.32K | BI50: -0.0739
B51: Feb 24 2025 | C51: 53.47 | D51: 5347 | E51: 145 | F51: 5347 | G51: Feb 24 2025 | H51: 7319810 | I51: 32900 | J51: 7319810 | M51: 45712 | N51: 53.47 | O51: 53.47 | P51: 53.47 | Q51: 53.47 | R51: 53.47 | S51: 145 | V51: 45663 | W51: 52.68 | X51: 55 | Y51: 58.75 | Z51: 51.25 | AA51: 39.05K | AB51: -0.0596 | AE51: 45847 | AF51: 81904.7 | AG51: 80904.4 | AH51: 81992.85 | AI51: 80733.07 | AJ51: 51.49M | AK51: 0.0148 | AM51: 14-09-2025 | AN51: 14.8 | AO51: 14.08 | AP51: 15.05 | AQ51: 13.82 | AR51: 2.78M | AS51: 0.0655 | AU51: 14-09-2025 | AV51: 38 | AW51: 38.3 | AX51: 39.89 | AY51: 36 | AZ51: 20.96K | BA51: -0.0021 | BC51: 14-09-2025 | BD51: 21.12 | BE51: 21.3 | BF51: 21.5 | BG51: 19.95 | BH51: 1.05M | BI51: -0.0009
B52: Feb 17 2025 | C52: 53.47 | D52: 5347 | E52: - | F52: 5347 | G52: Feb 17 2025 | H52: 7531106 | I52: 41400 | J52: 7531106 | M52: 45705 | N52: 53.47 | O52: 53.47 | P52: 53.47 | Q52: 53.47 | R52: 53.47 | S52: - | V52: 25-05-2025 | W52: 56.02 | X52: 54.1 | Y52: 60 | Z52: 52.25 | AA52: 13.35K | AB52: 0.0357 | AE52: 31-08-2025 | AF52: 80710.76 | AG52: 79828.99 | AH52: 81456.67 | AI52: 79818.38 | AJ52: 56.51M | AK52: 0.0113 | AM52: 45847 | AN52: 13.89 | AO52: 14 | AP52: 14.23 | AQ52: 13.73 | AR52: 923.83K | AS52: -0.0007 | AU52: 45847 | AV52: 38.08 | AW52: 36.5 | AX52: 38.49 | AY52: 34.5 | AZ52: 23.67K | BA52: 0.0433 | BC52: 45847 | BD52: 21.14 | BE52: 21 | BF52: 21.5 | BG52: 19.9 | BH52: 1.42M | BI52: 0.0217
B53: Feb 10 2025 | C53: 53.47 | D53: 5347 | E53: 277 | F53: 5347 | G53: Feb 10 2025 | H53: 7593921 | I53: 43400 | J53: 7593921 | M53: 45698 | N53: 53.47 | O53: 53.47 | P53: 48.51 | Q53: 53.47 | R53: 53.47 | S53: 277 | V53: 18-05-2025 | W53: 54.09 | X53: 57.99 | Y53: 57.99 | Z53: 53.6 | AA53: 6.71K | AB53: -0.0167 | AE53: 24-08-2025 | AF53: 79809.65 | AG53: 81501.06 | AH53: 81799.06 | AI53: 79741.76 | AJ53: 50.49M | AK53: -0.0184 | AM53: 31-08-2025 | AN53: 13.9 | AO53: 13.32 | AP53: 14.15 | AQ53: 12.56 | AR53: 1.36M | AS53: 0.0236 | AU53: 31-08-2025 | AV53: 36.5 | AW53: 34.22 | AX53: 37.25 | AY53: 34.1 | AZ53: 42.75K | BA53: 0.0178 | BC53: 31-08-2025 | BD53: 20.69 | BE53: 21.13 | BF53: 21.7 | BG53: 19.4 | BH53: 393.16K | BI53: -0.0208
B54: Feb 3 2025 | C54: 48.51 | D54: 4851 | E54: - | F54: 4851 | G54: Feb 3 2025 | H54: 7786019 | I54: 50100 | J54: 7786019 | M54: 45691 | N54: 48.51 | O54: 48.51 | P54: 48.51 | Q54: 48.51 | R54: 48.51 | S54: - | V54: 45966 | W54: 55.01 | X54: 58 | Y54: 58 | Z54: 54 | AA54: 3.99K | AB54: 0.0095 | AE54: 17-08-2025 | AF54: 81306.85 | AG54: 81315.79 | AH54: 82231.17 | AI54: 81202.42 | AJ54: 56.30M | AK54: 0.0088 | AM54: 24-08-2025 | AN54: 13.58 | AO54: 13.72 | AP54: 14.01 | AQ54: 13.48 | AR54: 512.91K | AS54: -0.0167 | AU54: 24-08-2025 | AV54: 35.86 | AW54: 34 | AX54: 36.75 | AY54: 34 | AZ54: 26.58K | BA54: 0.0056 | BC54: 24-08-2025 | BD54: 21.13 | BE54: 21.12 | BF54: 22.1 | BG54: 20.03 | BH54: 275.87K | BI54: 0.0005
B55: Jan 27 2025 | C55: 48.51 | D55: 4851 | E55: - | F55: 4851 | G55: Jan 27 2025 | H55: 7750057 | I55: 63800 | J55: 7750057 | M55: 45684 | N55: 48.51 | O55: 48.51 | P55: 48.51 | Q55: 48.51 | R55: 48.51 | S55: - | V55: 45752 | W55: 54.49 | X55: 60.49 | Y55: 60.49 | Z55: 50.02 | AA55: 5.24K | AB55: -0.0146 | AE55: 45938 | AF55: 80597.66 | AG55: 79885.36 | AH55: 80997.67 | AI55: 79772.46 | AJ55: 38.48M | AK55: 0.0093 | AM55: 17-08-2025 | AN55: 13.81 | AO55: 13.89 | AP55: 14.5 | AQ55: 13.5 | AR55: 708.23K | AS55: 0.0102 | AU55: 17-08-2025 | AV55: 35.66 | AW55: 34.1 | AX55: 36.98 | AY55: 33.05 | AZ55: 54.03K | BA55: 0.0128 | BC55: 17-08-2025 | BD55: 21.12 | BE55: 20.14 | BF55: 21.7 | BG55: 19.16 | BH55: 900.81K | BI55: 0.0476
B56: Jan 20 2025 | C56: 48.51 | D56: 4851 | E56: - | F56: 4851 | G56: Jan 20 2025 | H56: 7619046 | I56: 79200 | J56: 7619046 | M56: 45677 | N56: 48.51 | O56: 48.51 | P56: 48.51 | Q56: 48.51 | R56: 48.51 | S56: - | V56: 27-04-2025 | W56: 55.3 | X56: 54.9 | Y56: 58 | Z56: 53.6 | AA56: 6.26K | AB56: 0.0501 | AE56: 45724 | AF56: 79857.79 | AG56: 80765.83 | AH56: 81093.19 | AI56: 79775.84 | AJ56: 86.78M | AK56: -0.0092 | AM56: 45938 | AN56: 13.67 | AO56: 13.74 | AP56: 14 | AQ56: 13.51 | AR56: 1.45M | AS56: -0.0051 | AU56: 45938 | AV56: 35.21 | AW56: 32.26 | AX56: 37 | AY56: 32.26 | AZ56: 37.49K | BA56: 0.0473 | BC56: 45938 | BD56: 20.16 | BE56: 20.89 | BF56: 20.89 | BG56: 19 | BH56: 160.94K | BI56: 0.0085
B57: Jan 13 2025 | C57: 48.51 | D57: 4851 | E57: - | F57: 4851 | G57: Jan 13 2025 | H57: 7661933 | I57: 61500 | J57: 7661933 | M57: 45670 | N57: 48.51 | O57: 48.51 | P57: 48.51 | Q57: 48.51 | R57: 48.51 | S57: - | V57: 20-04-2025 | W57: 52.66 | X57: 59.99 | Y57: 60.49 | Z57: 48.55 | AA57: 14.11K | AB57: -0.0737 | AE57: 27-07-2025 | AF57: 80599.91 | AG57: 81299.97 | AH57: 81803.27 | AI57: 80495.57 | AJ57: 49.03M | AK57: -0.0106 | AM57: 45724 | AN57: 13.74 | AO57: 13.7 | AP57: 13.97 | AQ57: 13.33 | AR57: 2.11M | AS57: -0.0065 | AU57: 45724 | AV57: 33.62 | AW57: 38.5 | AX57: 38.7 | AY57: 33.2 | AZ57: 112.61K | BA57: -0.115 | BC57: 45724 | BD57: 19.99 | BE57: 20.15 | BF57: 20.75 | BG57: 19.5 | BH57: 414.16K | BI57: -0.0109
B58: Jan 6 2025 | C58: 48.51 | D58: 4851 | E58: - | F58: 4851 | G58: Jan 6 2025 | H58: 7737891 | I58: 46600 | J58: 7737891 | M58: 45663 | N58: 48.51 | O58: 48.51 | P58: 48.51 | Q58: 48.51 | R58: 48.51 | S58: - | V58: 13-04-2025 | W58: 56.85 | X58: 55.86 | Y58: 64 | Z58: 54.5 | AA58: 4.87K | AB58: 0.0538 | AE58: 20-07-2025 | AF58: 81463.09 | AG58: 81918.53 | AH58: 82786.43 | AI58: 81397.69 | AJ58: 73.24M | AK58: -0.0036 | AM58: 27-07-2025 | AN58: 13.83 | AO58: 13.99 | AP58: 14.17 | AQ58: 13.01 | AR58: 2.26M | AS58: 0.0007 | AU58: 27-07-2025 | AV58: 37.99 | AW58: 42.34 | AX58: 42.34 | AY58: 34.5 | AZ58: 136.28K | BA58: -0.1474 | BC58: 27-07-2025 | BD58: 20.21 | BE58: 18 | BF58: 20.9 | BG58: 17 | BH58: 463.90K | BI58: 0.1418
B59: Dec 30 2024 | C59: 48.51 | D59: 4851 | E59: 40 | F59: 4851 | G59: Dec 30 2024 | H59: 7922311 | I59: 39500 | J59: 7922311 | M59: 45656 | N59: 48.51 | O59: 48.51 | P59: 48.51 | Q59: 48.51 | R59: 48.51 | S59: 40 | V59: 45812 | W59: 53.95 | X59: 55.02 | Y59: 60.8 | Z59: 49.05 | AA59: 16.34K | AB59: -0.0194 | AE59: 13-07-2025 | AF59: 81757.73 | AG59: 82537.87 | AH59: 82784.75 | AI59: 81608.13 | AJ59: 52.66M | AK59: -0.009 | AM59: 20-07-2025 | AN59: 13.82 | AO59: 14.57 | AP59: 14.87 | AQ59: 13.41 | AR59: 3.85M | AS59: -0.0515 | AU59: 20-07-2025 | AV59: 44.56 | AW59: 39.8 | AX59: 56.39 | AY59: 39.8 | AZ59: 884.28K | BA59: 0.1399 | BC59: 20-07-2025 | BD59: 17.7 | BE59: 18.2 | BF59: 19 | BG59: 17.5 | BH59: 203.47K | BI59: -0.0396
B60: Dec 23 2024 | C60: 48.51 | D60: 4851 | E60: - | F60: 4851 | G60: Dec 23 2024 | H60: 7869907 | I60: 29800 | J60: 7869907 | M60: 45649 | N60: 48.51 | O60: 48.51 | P60: 48.51 | Q60: 48.51 | R60: 48.51 | S60: - | V60: 30-03-2025 | W60: 55.02 | X60: 50.39 | Y60: 56.99 | Z60: 50 | AA60: 16.32K | AB60: 0.0973 | AE60: 45815 | AF60: 82500.47 | AG60: 83398.08 | AH60: 83812.31 | AI60: 82442.25 | AJ60: 47.63M | AK60: -0.0112 | AM60: 13-07-2025 | AN60: 14.57 | AO60: 14.75 | AP60: 15.99 | AQ60: 14.5 | AR60: 5.05M | AS60: -0.0048 | AU60: 13-07-2025 | AV60: 39.09 | AW60: 27.06 | AX60: 40.28 | AY60: 27.06 | AZ60: 522.82K | BA60: 0.3769 | BC60: 13-07-2025 | BD60: 18.43 | BE60: 17.3 | BF60: 19.2 | BG60: 16.93 | BH60: 484.99K | BI60: 0.086
B61: Dec 16 2024 | C61: 48.51 | D61: 4851 | E61: 30 | F61: 4851 | G61: Dec 16 2024 | H61: 7804159 | I61: 30300 | J61: 7804159 | M61: 45642 | N61: 48.51 | O61: 48.51 | P61: 48.51 | Q61: 48.51 | R61: 48.51 | S61: 30 | V61: 23-03-2025 | W61: 50.14 | X61: 52.01 | Y61: 58 | Z61: 48.05 | AA61: 24.36K | AB61: -0.0985 | AE61: 29-06-2025 | AF61: 83432.89 | AG61: 84027.33 | AH61: 84099.53 | AI61: 83015.83 | AJ61: 54.23M | AK61: -0.0074 | AM61: 45815 | AN61: 14.64 | AO61: 14.84 | AP61: 15.25 | AQ61: 14.5 | AR61: 1.89M | AS61: -0.0135 | AU61: 45815 | AV61: 28.39 | AW61: 26.37 | AX61: 30.01 | AY61: 26.37 | AZ61: 136.34K | BA61: 0.0766 | BC61: 45815 | BD61: 16.97 | BE61: 16.25 | BF61: 17.3 | BG61: 15.4 | BH61: 612.39K | BI61: 0.0462
B62: Dec 9 2024 | C62: 48.51 | D62: 4851 | E62: 1 | F62: 4851 | G62: Dec 9 2024 | H62: 8213312 | I62: 37400 | J62: 8213312 | M62: 45635 | N62: 48.51 | O62: 48.51 | P62: 48.51 | Q62: 48.51 | R62: 48.51 | S62: 1 | V62: 16-03-2025 | W62: 55.62 | X62: 53.2 | Y62: 57.9 | Z62: 52.7 | AA62: 10.09K | AB62: 0.0484 | AE62: 22-06-2025 | AF62: 84058.9 | AG62: 81704.07 | AH62: 84089.35 | AI62: 81476.76 | AJ62: 153.91M | AK62: 0.02 | AM62: 29-06-2025 | AN62: 14.84 | AO62: 14.4 | AP62: 15 | AQ62: 14.06 | AR62: 2.22M | AS62: 0.0306 | AU62: 29-06-2025 | AV62: 26.37 | AW62: 27.98 | AX62: 27.99 | AY62: 26 | AZ62: 139.04K | BA62: -0.0575 | BC62: 29-06-2025 | BD62: 16.22 | BE62: 12.06 | BF62: 18.25 | BG62: 12.06 | BH62: 680.53K | BI62: 0.3187
B63: Dec 2 2024 | C63: 46.2 | D63: 4620 | E63: - | F63: 4620 | G63: Dec 2 2024 | H63: 8170912 | I63: 40200 | J63: 8170912 | M63: 45628 | N63: 46.2 | O63: 46.2 | P63: 46.2 | Q63: 46.2 | R63: 46.2 | S63: - | V63: 45903 | W63: 53.05 | X63: 57.9 | Y63: 59 | Z63: 48.05 | AA63: 8.37K | AB63: -0.0512 | AE63: 15-06-2025 | AF63: 82408.17 | AG63: 81034.45 | AH63: 82494.49 | AI63: 81012.31 | AJ63: 63.38M | AK63: 0.0159 | AM63: 22-06-2025 | AN63: 14.4 | AO63: 14.4 | AP63: 15.21 | AQ63: 14.3 | AR63: 3.44M | AS63: -0.0211 | AU63: 22-06-2025 | AV63: 27.98 | AW63: 28.6 | AX63: 29 | AY63: 25.8 | AZ63: 47.33K | BA63: 0.0351 | BC63: 22-06-2025 | BD63: 12.3 | BE63: 12 | BF63: 12.65 | BG63: 11.8 | BH63: 25.00K | BI63: 0.0008
B64: Nov 25 2024 | C64: 46.2 | D64: 4620 | E64: - | F64: 4620 | G64: Nov 25 2024 | H64: 7980279 | I64: 46900 | J64: 7980279 | M64: 45621 | N64: 46.2 | O64: 46.2 | P64: 46.2 | Q64: 46.2 | R64: 46.2 | S64: - | V64: 45691 | W64: 55.91 | X64: 57.15 | Y64: 59 | Z64: 52 | AA64: 12.02K | AB64: -0.0413 | AE64: 45875 | AF64: 81118.6 | AG64: 82574.55 | AH64: 82783.51 | AI64: 80354.59 | AJ64: 50.43M | AK64: -0.013 | AM64: 15-06-2025 | AN64: 14.71 | AO64: 14.77 | AP64: 15.44 | AQ64: 14.35 | AR64: 2.72M | AS64: -0.0088 | AU64: 15-06-2025 | AV64: 27.03 | AW64: 29.56 | AX64: 30 | AY64: 26.56 | AZ64: 83.48K | BA64: -0.0492 | BC64: 15-06-2025 | BD64: 12.29 | BE64: 11.85 | BF64: 12.74 | BG64: 11.8 | BH64: 37.01K | BI64: 0.0328
B65: Nov 18 2024 | C65: 46.2 | D65: 4620 | E65: - | F65: 4620 | G65: Nov 18 2024 | H65: 7911711 | I65: 41300 | J65: 7911711 | M65: 45614 | N65: 46.2 | O65: 46.2 | P65: 46.2 | Q65: 46.2 | R65: 46.2 | S65: - | V65: 23-02-2025 | W65: 58.32 | X65: 57 | Y65: 64.75 | Z65: 53 | AA65: 13.18K | AB65: 0.028 | AE65: 45663 | AF65: 82188.99 | AG65: 81214.42 | AH65: 82299.89 | AI65: 80575.09 | AJ65: 71.50M | AK65: 0.0091 | AM65: 45875 | AN65: 14.84 | AO65: 15 | AP65: 15.15 | AQ65: 14.27 | AR65: 1.78M | AS65: -0.0007 | AU65: 45875 | AV65: 28.43 | AW65: 25.9 | AX65: 31 | AY65: 25.1 | AZ65: 77.93K | BA65: 0.0935 | BC65: 45875 | BD65: 11.9 | BE65: 11.39 | BF65: 14 | BG65: 11.39 | BH65: 104.76K | BI65: 0.0162
B66: Nov 11 2024 | C66: 46.2 | D66: 4620 | E66: - | F66: 4620 | G66: Nov 11 2024 | H66: 7758031 | I66: 40800 | J66: 7758031 | M66: 45607 | N66: 46.2 | O66: 46.2 | P66: 46.2 | Q66: 46.2 | R66: 46.2 | S66: - | V66: 16-02-2025 | W66: 56.73 | X66: 53.51 | Y66: 61.2 | Z66: 48.82 | AA66: 10.45K | AB66: 0.0602 | AE66: 25-05-2025 | AF66: 81451.01 | AG66: 81928.95 | AH66: 82492.24 | AI66: 81106.98 | AJ66: 74.32M | AK66: -0.0033 | AM66: 45663 | AN66: 14.85 | AO66: 14.94 | AP66: 15.48 | AQ66: 14 | AR66: 2.98M | AS66: -0.0172 | AU66: 45663 | AV66: 26 | AW66: 25.59 | AX66: 27.59 | AY66: 25 | AZ66: 39.99K | BA66: 0.0363 | BC66: 45663 | BD66: 11.71 | BE66: 11.99 | BF66: 11.99 | BG66: 11.25 | BH66: 24.21K | BI66: 0.0026
B67: Nov 4 2024 | C67: 46.2 | D67: 4620 | E67: - | F67: 4620 | G67: Nov 4 2024 | H67: 7948632 | I67: 56800 | J67: 7948632 | M67: 45600 | N67: 46.2 | O67: 46.2 | P67: 46.2 | Q67: 46.2 | R67: 46.2 | S67: - | V67: 45902 | W67: 53.51 | X67: 66 | Y67: 66 | Z67: 53.35 | AA67: 24.22K | AB67: -0.1221 | AE67: 18-05-2025 | AF67: 81721.08 | AG67: 82354.92 | AH67: 82424.1 | AI67: 80489.92 | AJ67: 47.02M | AK67: -0.0074 | AM67: 25-05-2025 | AN67: 15.11 | AO67: 13.99 | AP67: 15.51 | AQ67: 13.9 | AR67: 3.99M | AS67: 0.0801 | AU67: 25-05-2025 | AV67: 25.09 | AW67: 25.94 | AX67: 25.94 | AY67: 24.95 | AZ67: 307.85K | BA67: 0.0036 | BC67: 25-05-2025 | BD67: 11.68 | BE67: 11.92 | BF67: 12.45 | BG67: 11.43 | BH67: 37.56K | BI67: -0.0395
B68: Oct 28 2024 | C68: 46.2 | D68: 4620 | E68: - | F68: 4620 | G68: Oct 28 2024 | H68: 7972412 | I68: 37900 | J68: 7972412 | M68: 45593 | N68: 46.2 | O68: 46.2 | P68: 46.2 | Q68: 46.2 | R68: 46.2 | S68: - | V68: 45690 | W68: 60.95 | X68: 60.1 | Y68: 64.86 | Z68: 56 | AA68: 7.88K | AB68: -0.0248 | AE68: 45966 | AF68: 82330.59 | AG68: 80803.8 | AH68: 82718.14 | AI68: 80651.07 | AJ68: 70.04M | AK68: 0.0362 | AM68: 18-05-2025 | AN68: 13.99 | AO68: 14 | AP68: 14.32 | AQ68: 13.8 | AR68: 732.38K | AS68: -0.0099 | AU68: 18-05-2025 | AV68: 25 | AW68: 26 | AX68: 27.49 | AY68: 25 | AZ68: 292.80K | BA68: -0.0177 | BC68: 18-05-2025 | BD68: 12.16 | BE68: 12.25 | BF68: 12.5 | BG68: 11.77 | BH68: 15.16K | BI68: -0.0073
B69: Oct 21 2024 | C69: 46.2 | D69: 4620 | E69: - | F69: 4620 | G69: Oct 21 2024 | H69: 7940229 | I69: 38100 | J69: 7940229 | M69: 45586 | N69: 46.2 | O69: 46.2 | P69: 46.2 | Q69: 46.2 | R69: 46.2 | S69: - | V69: 26-01-2025 | W69: 62.5 | X69: 60.03 | Y69: 65.86 | Z69: 56.3 | AA69: 10.74K | AB69: 0.0008 | AE69: 45752 | AF69: 79454.47 | AG69: 80661.62 | AH69: 81049.03 | AI69: 78968.34 | AJ69: 49.35M | AK69: -0.013 | AM69: 45966 | AN69: 14.13 | AO69: 13.6 | AP69: 14.52 | AQ69: 13.4 | AR69: 1.55M | AS69: 0.0624 | AU69: 45966 | AV69: 25.45 | AW69: 25.45 | AX69: 25.96 | AY69: 25.25 | AZ69: 300.01K | BA69: 0.0059 | BC69: 45966 | BD69: 12.25 | BE69: 11 | BF69: 12.83 | BG69: 11 | BH69: 38.96K | BI69: 0.1197
B70: Oct 14 2024 | C70: 46.2 | D70: 4620 | E70: 208 | F70: 4620 | G70: Oct 14 2024 | H70: 8122475 | I70: 34900 | J70: 8122475 | M70: 45579 | N70: 46.2 | O70: 46.2 | P70: 41.8 | Q70: 46.2 | R70: 46.2 | S70: 208 | V70: 19-01-2025 | W70: 62.45 | X70: 63.9 | Y70: 63.9 | Z70: 60 | AA70: 3.32K | AB70: 0.0027 | AE70: 27-04-2025 | AF70: 80501.99 | AG70: 79343.63 | AH70: 81177.93 | AI70: 79341.35 | AJ70: 49.57M | AK70: 0.0163 | AM70: 45752 | AN70: 13.3 | AO70: 13.8 | AP70: 14.1 | AQ70: 12.73 | AR70: 785.34K | AS70: -0.0369 | AU70: 45752 | AV70: 25.3 | AW70: 27 | AX70: 27 | AY70: 25.25 | AZ70: 142.60K | BA70: 0 | BC70: 45752 | BD70: 10.94 | BE70: 11.74 | BF70: 11.74 | BG70: 10.6 | BH70: 32.43K | BI70: -0.0462
B71: Oct 7 2024 | C71: 44 | D71: 4400 | E71: - | F71: 4400 | G71: Oct 7 2024 | H71: 8138136 | I71: 48700 | J71: 8138136 | M71: 45572 | N71: 44 | O71: 44 | P71: 44 | Q71: 44 | R71: 44 | S71: - | V71: 45992 | W71: 62.28 | X71: 64.37 | Y71: 64.37 | Z71: 59.41 | AA71: 8.00K | AB71: -0.0132 | AE71: 20-04-2025 | AF71: 79212.53 | AG71: 78903.09 | AH71: 80254.55 | AI71: 78605.81 | AJ71: 60.87M | AK71: 0.0084 | AM71: 27-04-2025 | AN71: 13.81 | AO71: 13.6 | AP71: 15 | AQ71: 13.6 | AR71: 2.32M | AS71: 0.0345 | AU71: 27-04-2025 | AV71: 25.3 | AW71: 25.3 | AX71: 25.96 | AY71: 25.25 | AZ71: 19.82K | BA71: 0.002 | BC71: 27-04-2025 | BD71: 11.47 | BE71: 11.76 | BF71: 12.49 | BG71: 11.15 | BH71: 50.30K | BI71: -0.0361
B72: Sep 30 2024 | C72: 44 | D72: 4400 | E72: 220 | F72: 4400 | G72: Sep 30 2024 | H72: 8168845 | I72: 55900 | J72: 8168845 | M72: 45565 | N72: 44 | O72: 44 | P72: 44 | Q72: 44 | R72: 44 | S72: 220 | V72: 45778 | W72: 63.11 | X72: 65.1 | Y72: 68.25 | Z72: 55 | AA72: 15.83K | AB72: -0.0378 | AE72: 13-04-2025 | AF72: 78553.2 | AG72: 76852.06 | AH72: 78616.77 | AI72: 76435.07 | AJ72: 33.54M | AK72: 0.0452 | AM72: 20-04-2025 | AN72: 13.35 | AO72: 14.35 | AP72: 14.83 | AQ72: 12.99 | AR72: 1.93M | AS72: -0.034 | AU72: 20-04-2025 | AV72: 25.25 | AW72: 25.3 | AX72: 25.5 | AY72: 25.25 | AZ72: 64.24K | BA72: -0.0098 | BC72: 20-04-2025 | BD72: 11.9 | BE72: 12.49 | BF72: 12.97 | BG72: 10.51 | BH72: 125.25K | BI72: -0.0472
B73: Sep 23 2024 | C73: 45 | D73: 4500 | E73: - | F73: 4500 | G73: Sep 23 2024 | H73: 8557185 | I73: 51800 | J73: 8557185 | M73: 45558 | N73: 45 | O73: 45 | P73: 45 | Q73: 45 | R73: 45 | S73: - | V73: 29-12-2024 | W73: 65.59 | X73: 66.49 | Y73: 70.99 | Z73: 63.21 | AA73: 13.32K | AB73: -0.0135 | AE73: 45812 | AF73: 75157.26 | AG73: 71449.94 | AH73: 75467.33 | AI73: 71425.01 | AJ73: 69.81M | AK73: -0.0028 | AM73: 13-04-2025 | AN73: 13.82 | AO73: 14.65 | AP73: 14.79 | AQ73: 13.45 | AR73: 1.51M | AS73: -0.0376 | AU73: 13-04-2025 | AV73: 25.5 | AW73: 25.43 | AX73: 25.55 | AY73: 25.3 | AZ73: 15.78K | BA73: 0.0028 | BC73: 13-04-2025 | BD73: 12.49 | BE73: 12.6 | BF73: 12.72 | BG73: 11.92 | BH73: 23.84K | BI73: -0.0064
B74: Sep 16 2024 | C74: 45 | D74: 4500 | E74: - | F74: 4500 | G74: Sep 16 2024 | H74: 8454431 | I74: 57100 | J74: 8454431 | M74: 45551 | N74: 45 | O74: 45 | P74: 45 | Q74: 45 | R74: 45 | S74: - | V74: 22-12-2024 | W74: 66.49 | X74: 66.87 | Y74: 70.7 | Z74: 62.07 | AA74: 8.96K | AB74: 0.0142 | AE74: 30-03-2025 | AF74: 75364.69 | AG74: 76882.58 | AH74: 77487.05 | AI74: 75240.55 | AJ74: 39.94M | AK74: -0.0265 | AM74: 45812 | AN74: 14.36 | AO74: 12.51 | AP74: 14.94 | AQ74: 12.51 | AR74: 1.55M | AS74: -0.0055 | AU74: 45812 | AV74: 25.43 | AW74: 25.47 | AX74: 25.5 | AY74: 25.3 | AZ74: 10.98K | BA74: -0.0024 | BC74: 45812 | BD74: 12.57 | BE74: 13.01 | BF74: 13.23 | BG74: 11.87 | BH74: 16.10K | BI74: -0.0845
B75: Sep 9 2024 | C75: 45 | D75: 4500 | E75: 8 | F75: 4500 | G75: Sep 9 2024 | H75: 8289094 | I75: 42200 | J75: 8289094 | M75: 45544 | N75: 45 | O75: 45 | P75: 45 | Q75: 45 | R75: 45 | S75: 8 | V75: 15-12-2024 | W75: 65.56 | X75: 72.72 | Y75: 75 | Z75: 65.25 | AA75: 23.53K | AB75: -0.0599 | AE75: 23-03-2025 | AF75: 77414.92 | AG75: 77456.27 | AH75: 78741.69 | AI75: 77082.51 | AJ75: 62.62M | AK75: 0.0066 | AM75: 30-03-2025 | AN75: 14.44 | AO75: 14.19 | AP75: 15.25 | AQ75: 13.23 | AR75: 2.21M | AS75: 0.0833 | AU75: 30-03-2025 | AV75: 25.49 | AW75: 25.35 | AX75: 26.5 | AY75: 25.25 | AZ75: 8.95K | BA75: 0.0075 | BC75: 30-03-2025 | BD75: 13.73 | BE75: 11.25 | BF75: 14.32 | BG75: 10.75 | BH75: 67.45K | BI75: 0.282
B76: Sep 2 2024 | C76: 46 | D76: 4600 | E76: 24 | F76: 4600 | G76: Sep 2 2024 | H76: 8118393 | I76: 44400 | J76: 8118393 | M76: 45537 | N76: 46 | O76: 46 | P76: 45.3 | Q76: 46 | R76: 46 | S76: 24 | V76: 45516 | W76: 69.74 | X76: 73 | Y76: 73 | Z76: 66.22 | AA76: 23.49K | AB76: 0.0355 | AE76: 16-03-2025 | AF76: 76905.51 | AG76: 73830.03 | AH76: 77041.94 | AI76: 73796.06 | AJ76: 51.67M | AK76: 0.0417 | AM76: 23-03-2025 | AN76: 13.33 | AO76: 14.97 | AP76: 14.97 | AQ76: 12.25 | AR76: 2.51M | AS76: -0.073 | AU76: 23-03-2025 | AV76: 25.3 | AW76: 26.01 | AX76: 26.01 | AY76: 25.25 | AZ76: 25.32K | BA76: -0.0078 | BC76: 23-03-2025 | BD76: 10.71 | BE76: 12.85 | BF76: 12.99 | BG76: 10.56 | BH76: 81.47K | BI76: -0.1665
B77: Aug 26 2024 | C77: 46.2 | D77: 4620 | E77: - | F77: 4620 | G77: Aug 26 2024 | H77: 8236577 | I77: 45700 | J77: 8236577 | M77: 45530 | N77: 46.2 | O77: 46.2 | P77: 46.2 | Q77: 46.2 | R77: 46.2 | V77: 45303 | W77: 67.35 | X77: 64 | Y77: 69.99 | Z77: 62.27 | AA77: 35.18K | AB77: 0.0362 | AE77: 45903 | AF77: 73828.91 | AG77: 74474.98 | AH77: 74741.25 | AI77: 73598.16 | AJ77: 42.02M | AK77: -0.0068 | AM77: 16-03-2025 | AN77: 14.38 | AO77: 12.5 | AP77: 16.35 | AQ77: 12.2 | AR77: 4.10M | AS77: 0.1597 | AU77: 16-03-2025 | AV77: 25.5 | AW77: 25.3 | AX77: 25.5 | AY77: 25.3 | AZ77: 41.26K | BA77: 0 | BC77: 16-03-2025 | BD77: 12.85 | BE77: 13.17 | BF77: 13.17 | BG77: 12.27 | BH77: 55.05K | BI77: 0.0008
B78: Aug 19 2024 | C78: 46.2 | D78: 46.2 | E78: - | F78: 46.2 | G78: Aug 19 2024 | H78: 8108621 | I78: 38900 | J78: 8108621 | M78: 45523 | N78: 46.2 | O78: 46.2 | P78: 46.2 | Q78: 46.2 | R78: 46.2 | V78: 24-11-2024 | W78: 65 | X78: 65.9 | Y78: 71 | Z78: 57.35 | AA78: 18.50K | AB78: 0.0733 | AE78: 45691 | AF78: 74332.58 | AG78: 73427.65 | AH78: 74586.43 | AI78: 72633.54 | AJ78: 42.56M | AK78: 0.0155 | AM78: 45903 | AN78: 12.4 | AO78: 13.35 | AP78: 13.67 | AQ78: 12.11 | AR78: 1.01M | AS78: -0.0712 | AU78: 45903 | AV78: 25.5 | AW78: 25.3 | AX78: 25.5 | AY78: 25.3 | AZ78: 8.79K | BA78: 0.0067 | BC78: 45903 | BD78: 12.84 | BE78: 13.95 | BF78: 14 | BG78: 12.5 | BH78: 38.66K | BI78: -0.0789
B79: Aug 12 2024 | C79: 46.2 | D79: 46.2 | E79: - | F79: 46.2 | G79: Aug 12 2024 | H79: 8043684 | I79: 41700 | J79: 8043684 | M79: 45516 | N79: 46.2 | O79: 46.2 | P79: 46.2 | Q79: 46.2 | R79: 46.2 | V79: 17-11-2024 | W79: 60.56 | X79: 60.1 | Y79: 65.86 | Z79: 55.15 | AA79: 21.22K | AB79: 0.0077 | AE79: 23-02-2025 | AF79: 73198.1 | AG79: 74893.45 | AH79: 74907.04 | AI79: 73141.27 | AJ79: 32.92M | AK79: -0.0281 | AM79: 45691 | AN79: 13.35 | AO79: 12.8 | AP79: 13.47 | AQ79: 12 | AR79: 1.12M | AS79: 0.0462 | AU79: 45691 | AV79: 25.33 | AW79: 25.45 | AX79: 25.45 | AY79: 25.25 | AZ79: 44.45K | BA79: -0.0047 | BC79: 45691 | BD79: 13.94 | BE79: 13.92 | BF79: 14.47 | BG79: 13.21 | BH79: 60.50K | BI79: 0.0265
B80: Aug 5 2024 | C80: 46.2 | D80: 46.2 | E80: 155 | F80: 46.2 | G80: Aug 5 2024 | H80: 7970591 | I80: 60300 | J80: 7970591 | M80: 45509 | N80: 46.2 | O80: 46.2 | P80: 46.2 | Q80: 46.2 | R80: 46.2 | S80: 155 | V80: 45576 | W80: 60.1 | X80: 68.7 | Y80: 70.45 | Z80: 59.15 | AA80: 13.94K | AB80: -0.1076 | AE80: 16-02-2025 | AF80: 75311.06 | AG80: 75641.41 | AH80: 76338.58 | AI80: 75112.41 | AJ80: 41.41M | AK80: -0.0083 | AM80: 23-02-2025 | AN80: 12.76 | AO80: 13.05 | AP80: 13.29 | AQ80: 12.5 | AR80: 961.08K | AS80: -0.042 | AU80: 23-02-2025 | AV80: 25.45 | AW80: 25.92 | AX80: 25.92 | AY80: 25.3 | AZ80: 11.38K | BA80: 0.0016 | BC80: 23-02-2025 | BD80: 13.58 | BE80: 14.2 | BF80: 14.72 | BG80: 13.25 | BH80: 61.75K | BI80: -0.0463
B81: Jul 29 2024 | C81: 44 | D81: 44 | E81: 152 | F81: 44 | G81: Jul 29 2024 | H81: 8098195 | I81: 71100 | J81: 8098195 | M81: 45502 | N81: 44 | O81: 44.15 | P81: 41.71 | Q81: 44 | R81: 44 | S81: 152 | V81: 45362 | W81: 67.35 | X81: 75.99 | Y81: 75.99 | Z81: 64.8 | AA81: 20.82K | AB81: -0.0938 | AE81: 45902 | AF81: 75939.21 | AG81: 77789.3 | AH81: 77849.58 | AI81: 75388.39 | AJ81: 43.50M | AK81: -0.0247 | AM81: 16-02-2025 | AN81: 13.32 | AO81: 13.2 | AP81: 13.8 | AQ81: 12.75 | AR81: 1.05M | AS81: 0.0302 | AU81: 16-02-2025 | AV81: 25.41 | AW81: 25.45 | AX81: 25.82 | AY81: 25.3 | AZ81: 36.46K | BA81: -0.0035 | BC81: 16-02-2025 | BD81: 14.24 | BE81: 15.13 | BF81: 15.13 | BG81: 13.3 | BH81: 43.19K | BI81: -0.0398
B82: Jul 22 2024 | C82: 41 | D82: 41 | E82: 35 | F82: 41 | G82: Jul 22 2024 | H82: 8133272 | I82: 62500 | J82: 8133272 | M82: 45495 | N82: 41 | O82: 41.89 | P82: 41 | Q82: 41 | R82: 41 | S82: 35 | V82: 27-10-2024 | W82: 74.32 | X82: 65 | Y82: 77.7 | Z82: 63.2 | AA82: 23.21K | AB82: 0.139 | AE82: 45690 | AF82: 77860.19 | AG82: 77637.01 | AH82: 78735.41 | AI82: 76756.09 | AJ82: 66.01M | AK82: 0.0219 | AM82: 45902 | AN82: 12.93 | AO82: 14.9 | AP82: 14.9 | AQ82: 12.15 | AR82: 1.71M | AS82: -0.1328 | AU82: 45902 | AV82: 25.5 | AW82: 26 | AX82: 26.72 | AY82: 25.3 | AZ82: 349.54K | BA82: 0.0059 | BC82: 45902 | BD82: 14.83 | BE82: 15.04 | BF82: 15.89 | BG82: 13.33 | BH82: 50.79K | BI82: -0.014
B83: Jul 15 2024 | C83: 41.89 | D83: 41.89 | E83: - | F83: 41.89 | G83: Jul 15 2024 | H83: 8060465 | I83: 50300 | J83: 8060465 | M83: 45488 | N83: 41.89 | O83: 41.89 | P83: 41.89 | Q83: 41.89 | R83: 41.89 | V83: 20-10-2024 | W83: 65.25 | X83: 75 | Y83: 75.37 | Z83: 62.5 | AA83: 69.50K | AB83: -0.0477 | AE83: 26-01-2025 | AF83: 76190.46 | AG83: 76978.53 | AH83: 77337.36 | AI83: 75641.87 | AJ83: 79.32M | AK83: -0.0056 | AM83: 45690 | AN83: 14.91 | AO83: 14.9 | AP83: 15.83 | AQ83: 13.41 | AR83: 3.33M | AS83: 0.0136 | AU83: 45690 | AV83: 25.35 | AW83: 25.25 | AX83: 26 | AY83: 25.15 | AZ83: 204.80K | BA83: 0.006 | BC83: 45690 | BD83: 15.04 | BE83: 15.99 | BF83: 15.99 | BG83: 14.5 | BH83: 46.06K | BI83: -0.0131
B84: Jul 8 2024 | C84: 41.89 | D84: 41.89 | E84: - | F84: 41.89 | G84: Jul 8 2024 | H84: 8051934 | I84: 56200 | J84: 8051934 | M84: 45481 | N84: 41.89 | O84: 41.89 | P84: 41.89 | Q84: 41.89 | R84: 41.89 | V84: 13-10-2024 | W84: 68.52 | X84: 73 | Y84: 74.75 | Z84: 67 | AA84: 24.29K | AB84: -0.0729 | AE84: 19-01-2025 | AF84: 76619.33 | AG84: 76629.9 | AH84: 77319.5 | AI84: 76249.72 | AJ84: 61.53M | AK84: -0.0098 | AM84: 26-01-2025 | AN84: 14.71 | AO84: 16.44 | AP84: 16.44 | AQ84: 14.2 | AR84: 1.32M | AS84: -0.0975 | AU84: 26-01-2025 | AV84: 25.2 | AW84: 30.7 | AX84: 30.7 | AY84: 25.2 | AZ84: 152.45K | BA84: -0.1628 | BC84: 26-01-2025 | BD84: 15.24 | BE84: 14.25 | BF84: 15.5 | BG84: 13.11 | BH84: 94.26K | BI84: 0.0687
B85: Jul 1 2024 | C85: 41.89 | D85: 41.89 | E85: 406 | F85: 41.89 | G85: Jul 1 2024 | H85: 7999660 | I85: 25000 | J85: 7999660 | M85: 45474 | N85: 41.89 | O85: 41.89 | P85: 41.89 | Q85: 41.89 | R85: 41.89 | S85: 406 | V85: 45453 | W85: 73.91 | X85: 80.99 | Y85: 80.99 | Z85: 71.9 | AA85: 50.77K | AB85: -0.0564 | AE85: 45992 | AF85: 77378.91 | AG85: 79281.65 | AH85: 79532.67 | AI85: 77099.55 | AJ85: 46.56M | AK85: -0.0233 | AM85: 19-01-2025 | AN85: 16.3 | AO85: 18.24 | AP85: 18.75 | AQ85: 16.25 | AR85: 625.76K | AS85: -0.1064 | AU85: 19-01-2025 | AV85: 30.1 | AW85: 35.1 | AX85: 35.5 | AY85: 30.01 | AZ85: 33.90K | BA85: -0.166 | BC85: 19-01-2025 | BD85: 14.26 | BE85: 14.4 | BF85: 14.96 | BG85: 13.76 | BH85: 30.33K | BI85: -0.0125
B86: Jun 24 2024 | C86: 39.9 | D86: 39.9 | E86: 40 | F86: 39.9 | G86: Jun 24 2024 | H86: 7903273 | I86: 58100 | J86: 7903273 | M86: 45467 | N86: 39.9 | O86: 39.9 | P86: 39.9 | Q86: 39.9 | R86: 39.9 | S86: 40 | V86: 29-09-2024 | W86: 78.33 | X86: 77.57 | Y86: 82 | Z86: 71.35 | AA86: 141.54K | AB86: 0.0434 | AE86: 45778 | AF86: 79223.11 | AG86: 78637.58 | AH86: 80072.99 | AI86: 77560.79 | AJ86: 39.45M | AK86: 0.0067 | AM86: 45992 | AN86: 18.24 | AO86: 17.8 | AP86: 19.09 | AQ86: 17.01 | AR86: 1.18M | AS86: 0.0253 | AU86: 45992 | AV86: 36.09 | AW86: 42.27 | AX86: 42.27 | AY86: 36 | AZ86: 25.54K | BA86: -0.1291 | BC86: 45992 | BD86: 14.44 | BE86: 14.5 | BF86: 14.92 | BG86: 13.01 | BH86: 97.42K | BI86: 0.0278
B87: Jun 17 2024 | C87: 39.9 | D87: 39.9 | E87: - | F87: 39.9 | G87: Jun 17 2024 | H87: 7720990 | I87: 50400 | J87: 7720990 | M87: 45460 | N87: 39.9 | O87: 39.9 | P87: 39.9 | Q87: 39.9 | R87: 39.9 | V87: 22-09-2024 | W87: 75.07 | X87: 79 | Y87: 79 | Z87: 72 | AA87: 46.28K | AB87: -0.0228 | AE87: 29-12-2024 | AF87: 78699.07 | AG87: 78488.64 | AH87: 79043.15 | AI87: 78173.38 | AJ87: 29.76M | AK87: 0.0084 | AM87: 45778 | AN87: 17.79 | AO87: 20.88 | AP87: 21.4 | AQ87: 17.64 | AR87: 1.35M | AS87: -0.1364 | AU87: 45778 | AV87: 41.44 | AW87: 49.5 | AX87: 49.5 | AY87: 41 | AZ87: 49.81K | BA87: -0.1456 | BC87: 45778 | BD87: 14.05 | BE87: 14.8 | BF87: 14.96 | BG87: 13.57 | BH87: 52.47K | BI87: -0.0455
B88: Jun 10 2024 | C88: 39.9 | D88: 39.9 | E88: 335 | F88: 39.9 | G88: Jun 10 2024 | H88: 7699277 | I88: 53600 | J88: 7699277 | M88: 45453 | N88: 39.9 | O88: 39.9 | P88: 38 | Q88: 39.9 | R88: 39.9 | S88: 335 | V88: 15-09-2024 | W88: 76.82 | X88: 77 | Y88: 81 | Z88: 73.66 | AA88: 71.97K | AB88: 0.0392 | AE88: 22-12-2024 | AF88: 78041.59 | AG88: 82000.31 | AH88: 82116.44 | AI88: 77874.59 | AJ88: 30.25M | AK88: -0.0498 | AM88: 29-12-2024 | AN88: 20.6 | AO88: 19.5 | AP88: 21.99 | AQ88: 18.25 | AR88: 2.24M | AS88: 0.0735 | AU88: 29-12-2024 | AV88: 48.5 | AW88: 57.5 | AX88: 57.9 | AY88: 48.45 | AZ88: 242.72K | BA88: -0.1565 | BC88: 29-12-2024 | BD88: 14.72 | BE88: 15.05 | BF88: 15.81 | BG88: 14.48 | BH88: 75.38K | BI88: -0.0265
B89: Jun 3 2024 | C89: 38 | D89: 38 | E89: - | F89: 38 | G89: Jun 3 2024 | H89: 7669336 | I89: 117900 | J89: 7669336 | M89: 45446 | N89: 38 | O89: 38 | P89: 38 | Q89: 38 | R89: 38 | V89: 45513 | W89: 73.92 | X89: 67.9 | Y89: 74.99 | Z89: 63.27 | AA89: 61.72K | AB89: 0.1101 | AE89: 15-12-2024 | AF89: 82133.12 | AG89: 81602.58 | AH89: 82213.92 | AI89: 80082.82 | AJ89: 37.36M | AK89: 0.0052 | AM89: 22-12-2024 | AN89: 19.19 | AO89: 20.8 | AP89: 21.28 | AQ89: 18.22 | AR89: 1.13M | AS89: -0.0774 | AU89: 22-12-2024 | AV89: 57.5 | AW89: 67 | AX89: 67 | AY89: 57.5 | AZ89: 124.69K | BA89: -0.1418 | BC89: 22-12-2024 | BD89: 15.12 | BE89: 15.89 | BF89: 15.99 | BG89: 15 | BH89: 19.25K | BI89: -0.0295
B90: May 27 2024 | C90: 38 | D90: 38 | E90: - | F90: 38 | G90: May 27 2024 | H90: 7396131 | I90: 56300 | J90: 7396131 | M90: 45439 | N90: 38 | O90: 38 | P90: 38 | Q90: 38 | R90: 38 | V90: 45300 | W90: 66.59 | X90: 77.3 | Y90: 80 | Z90: 65.1 | AA90: 81.30K | AB90: -0.1342 | AE90: 45516 | AF90: 81709.12 | AG90: 79743.87 | AH90: 82317.74 | AI90: 79308.95 | AJ90: 40.29M | AK90: 0.0239 | AM90: 15-12-2024 | AN90: 20.8 | AO90: 20.58 | AP90: 23 | AQ90: 18.02 | AR90: 4.95M | AS90: 0.0543 | AU90: 15-12-2024 | AV90: 67 | AW90: 68 | AX90: 70.5 | AY90: 66.6 | AZ90: 51.66K | BA90: -0.0074 | BC90: 15-12-2024 | BD90: 15.58 | BE90: 16.09 | BF90: 16.4 | BG90: 13.78 | BH90: 193.56K | BI90: -0.0244
B91: May 20 2024 | C91: 38 | D91: 38 | E91: 1 | F91: 38 | G91: May 20 2024 | H91: 7541039 | I91: 39400 | J91: 7541039 | M91: 45432 | N91: 38 | O91: 39.29 | P91: 38 | Q91: 38 | R91: 38 | S91: 1 | V91: 25-08-2024 | W91: 76.91 | X91: 81.76 | Y91: 89.93 | Z91: 75 | AA91: 449.25K | AB91: -0.0593 | AE91: 45303 | AF91: 79802.79 | AG91: 80193.47 | AH91: 80511.15 | AI91: 78918.92 | AJ91: 46.94M | AK91: 0.0087 | AM91: 45516 | AN91: 19.73 | AO91: 17.32 | AP91: 21.22 | AQ91: 17.32 | AR91: 6.14M | AS91: 0.1727 | AU91: 45516 | AV91: 67.5 | AW91: 62.45 | AX91: 68.55 | AY91: 61.25 | AZ91: 28.22K | BA91: 0.0809 | BC91: 45516 | BD91: 15.97 | BE91: 16.02 | BF91: 16.45 | BG91: 15.25 | BH91: 50.34K | BI91: 0.0063
B92: May 13 2024 | C92: 39.29 | D92: 39.29 | E92: - | F92: 39.29 | G92: May 13 2024 | H92: 7391703 | I92: 50300 | J92: 7391703 | M92: 45425 | N92: 39.29 | O92: 39.29 | P92: 39.29 | Q92: 39.29 | R92: 39.29 | V92: 18-08-2024 | W92: 81.76 | X92: 56.24 | Y92: 81.76 | Z92: 54.12 | AA92: 77.58K | AB92: 0.4538 | AE92: 24-11-2024 | AF92: 79117.11 | AG92: 77863.54 | AH92: 79218.19 | AI92: 76802.73 | AJ92: 41.26M | AK92: 0.0198 | AM92: 45303 | AN92: 16.82 | AO92: 16.42 | AP92: 17.28 | AQ92: 16.32 | AR92: 407.10K | AS92: 0.0246 | AU92: 45303 | AV92: 62.45 | AW92: 60.86 | AX92: 63.5 | AY92: 60.86 | AZ92: 1.50K | BA92: 0.0056 | BC92: 45303 | BD92: 15.87 | BE92: 15.61 | BF92: 16.43 | BG92: 15.5 | BH92: 75.03K | BI92: -0.005
B93: May 6 2024 | C93: 39.29 | D93: 39.29 | E93: 500 | F93: 39.29 | G93: May 6 2024 | H93: 7266447 | I93: 45800 | J93: 7266447 | M93: 45418 | N93: 39.29 | O93: 39.29 | P93: 39.29 | Q93: 39.29 | R93: 39.29 | S93: 500 | V93: 45604 | W93: 56.24 | X93: 55.21 | Y93: 66 | Z93: 53.65 | AA93: 28.97K | AB93: 0.0187 | AE93: 17-11-2024 | AF93: 77580.31 | AG93: 79298.46 | AH93: 80102.14 | AI93: 77424.81 | AJ93: 40.78M | AK93: -0.024 | AM93: 24-11-2024 | AN93: 16.42 | AO93: 15.84 | AP93: 16.63 | AQ93: 14.75 | AR93: 282.32K | AS93: 0.0571 | AU93: 24-11-2024 | AV93: 62.1 | AW93: 63.5 | AX93: 63.5 | AY93: 62.1 | AZ93: 2.07K | BA93: -0.0048 | BC93: 24-11-2024 | BD93: 15.95 | BE93: 15.13 | BF93: 16.58 | BG93: 15 | BH93: 65.09K | BI93: 0.0542
B94: Apr 29 2024 | C94: 41.35 | D94: 41.35 | E94: 200 | F94: 41.35 | G94: Apr 29 2024 | H94: 7387815 | I94: 52300 | J94: 7387815 | M94: 45411 | N94: 41.35 | O94: 41.35 | P94: 41.35 | Q94: 41.35 | R94: 41.35 | S94: 200 | V94: 45390 | W94: 55.21 | X94: 55.4 | Y94: 56.79 | Z94: 51.06 | AA94: 9.55K | AB94: 0.0203 | AE94: 45576 | AF94: 79486.32 | AG94: 79713.14 | AH94: 80569.73 | AI94: 78232.6 | AJ94: 56.84M | AK94: -0.003 | AM94: 17-11-2024 | AN94: 15.53 | AO94: 15.39 | AP94: 16.11 | AQ94: 14.67 | AR94: 250.13K | AS94: 0.0091 | AU94: 17-11-2024 | AV94: 62.4 | AW94: 62.5 | AX94: 64.5 | AY94: 62.4 | AZ94: 16.96K | BA94: -0.0016 | BC94: 17-11-2024 | BD94: 15.13 | BE94: 13.51 | BF94: 15.74 | BG94: 13.51 | BH94: 59.24K | BI94: 0.0363
B95: Apr 22 2024 | C95: 41.35 | D95: 41.35 | E95: 1062 | F95: 41.35 | G95: Apr 22 2024 | H95: 7373016 | I95: 49600 | J95: 7373016 | M95: 45404 | N95: 41.35 | O95: 41.35 | P95: 41.35 | Q95: 41.35 | R95: 41.35 | S95: 1062 | V95: 28-07-2024 | W95: 54.11 | X95: 55.87 | Y95: 57.9 | Z95: 53 | AA95: 14.89K | AB95: -0.0315 | AE95: 45362 | AF95: 79724.12 | AG95: 79653.67 | AH95: 80539.81 | AI95: 79287.93 | AJ95: 37.83M | AK95: 0.0041 | AM95: 45576 | AN95: 15.39 | AO95: 16.18 | AP95: 16.18 | AQ95: 14.55 | AR95: 251.92K | AS95: -0.0309 | AU95: 45576 | AV95: 62.5 | AW95: 62.75 | AX95: 62.75 | AY95: 62.5 | AZ95: 0.47K | BA95: -0.0048 | BC95: 45576 | BD95: 14.6 | BE95: 16.49 | BF95: 16.49 | BG95: 13.45 | BH95: 64.16K | BI95: -0.107
B96: Apr 15 2024 | C96: 41.39 | D96: 41.39 | E96: - | F96: 41.39 | G96: Apr 15 2024 | H96: 7308833 | I96: 50600 | J96: 7308833 | M96: 45397 | N96: 41.39 | O96: 41.39 | P96: 41.39 | Q96: 41.39 | R96: 41.39 | V96: 21-07-2024 | W96: 55.87 | X96: 55.5 | Y96: 58.78 | Z96: 51.06 | AA96: 27.52K | AB96: 0.0067 | AE96: 27-10-2024 | AF96: 79402.29 | AG96: 81770.02 | AH96: 81770.02 | AI96: 79137.98 | AJ96: 38.12M | AK96: -0.0224 | AM96: 45362 | AN96: 15.89 | AO96: 16.93 | AP96: 16.93 | AQ96: 15.71 | AR96: 337.48K | AS96: -0.0469 | AU96: 45362 | AV96: 62.8 | AW96: 64.05 | AX96: 64.05 | AY96: 62.8 | AZ96: 0.71K | BA96: -0.0049 | BC96: 45362 | BD96: 16.35 | BE96: 16.65 | BF96: 16.65 | BG96: 15.51 | BH96: 78.97K | BI96: -0.0168
B97: Apr 8 2024 | C97: 41.39 | D97: 41.39 | E97: - | F97: 41.39 | G97: Apr 8 2024 | H97: 7424490 | I97: 72000 | J97: 7424490 | M97: 45390 | N97: 41.39 | O97: 41.39 | P97: 41.39 | Q97: 41.39 | R97: 41.39 | V97: 14-07-2024 | W97: 55.5 | X97: 58.75 | Y97: 58.75 | Z97: 52 | AA97: 13.76K | AB97: -0.0292 | AE97: 20-10-2024 | AF97: 81224.75 | AG97: 81576.93 | AH97: 82300.44 | AI97: 80409.25 | AJ97: 34.90M | AK97: -0.0019 | AM97: 27-10-2024 | AN97: 16.67 | AO97: 15.37 | AP97: 16.91 | AQ97: 15.04 | AR97: 200.57K | AS97: 0.0532 | AU97: 27-10-2024 | AV97: 63.11 | AW97: 63.05 | AX97: 64.05 | AY97: 61.69 | AZ97: 1.60K | BA97: 0.001 | BC97: 27-10-2024 | BD97: 16.63 | BE97: 15.75 | BF97: 16.89 | BG97: 15.4 | BH97: 35.71K | BI97: 0.0426
B98: Apr 1 2024 | C98: 41.39 | D98: 41.39 | E98: - | F98: 41.39 | G98: Apr 1 2024 | H98: 7424822 | I98: 36200 | J98: 7424822 | M98: 45383 | N98: 41.39 | O98: 41.39 | P98: 41.39 | Q98: 41.39 | R98: 41.39 | V98: 45480 | W98: 57.17 | X98: 60.38 | Y98: 60.38 | Z98: 55 | AA98: 13.22K | AB98: -0.0106 | AE98: 13-10-2024 | AF98: 81381.36 | AG98: 81926.99 | AH98: 82319.21 | AI98: 80726.06 | AJ98: 48.63M | AK98: -0.0038 | AM98: 20-10-2024 | AN98: 15.82 | AO98: 17.55 | AP98: 17.98 | AQ98: 15.53 | AR98: 415.49K | AS98: -0.081 | AU98: 20-10-2024 | AV98: 63.05 | AW98: 62.9 | AX98: 64.21 | AY98: 62.9 | AZ98: 2.54K | BA98: 0.0016 | BC98: 20-10-2024 | BD98: 15.95 | BE98: 17.11 | BF98: 17.47 | BG98: 15.38 | BH98: 115.05K | BI98: -0.0711
B99: Mar 25 2024 | C99: 41.39 | D99: 41.39 | E99: 840 | F99: 41.39 | G99: Mar 25 2024 | H99: 7365135 | I99: 54900 | J99: 7365135 | M99: 45376 | N99: 41.39 | O99: 41.39 | P99: 41.39 | Q99: 41.39 | R99: 41.39 | S99: 840 | V99: 30-06-2024 | W99: 57.78 | X99: 56.32 | Y99: 58.75 | Z99: 53.95 | AA99: 20.33K | AB99: 0.0334 | AE99: 45453 | AF99: 81688.45 | AG99: 85208.76 | AH99: 85359.65 | AI99: 81532.68 | AJ99: 55.96M | AK99: -0.0454 | AM99: 13-10-2024 | AN99: 17.22 | AO99: 18.61 | AP99: 18.61 | AQ99: 16.76 | AR99: 506.60K | AS99: -0.0653 | AU99: 13-10-2024 | AV99: 62.95 | AW99: 63 | AX99: 64 | AY99: 62.95 | AZ99: 19.86K | BA99: -0.0164 | BC99: 13-10-2024 | BD99: 17.17 | BE99: 16.77 | BF99: 18.56 | BG99: 16.77 | BH99: 158.78K | BI99: 0.0088
B100: Mar 18 2024 | C100: 41.39 | D100: 41.39 | E100: 1679 | F100: 41.39 | G100: Mar 18 2024 | H100: 7283194 | I100: 96700 | J100: 7283194 | M100: 45369 | N100: 41.39 | O100: 41.39 | P100: 35.68 | Q100: 41.39 | R100: 41.39 | S100: 1679 | V100: 23-06-2024 | W100: 55.91 | X100: 60.5 | Y100: 60.5 | Z100: 55.1 | AA100: 23.38K | AB100: -0.0504 | AE100: 29-09-2024 | AF100: 85571.85 | AG100: 84651.15 | AH100: 85978.25 | AI100: 84607.38 | AJ100: 51.87M | AK100: 0.0122 | AM100: 45453 | AN100: 18.42 | AO100: 17.38 | AP100: 18.86 | AQ100: 15.53 | AR100: 645.14K | AS100: 0.0698 | AU100: 45453 | AV100: 64 | AW100: 66.63 | AX100: 66.63 | AY100: 61.75 | AZ100: 23.10K | BA100: -0.0154 | BC100: 45453 | BD100: 17.02 | BE100: 18.72 | BF100: 18.72 | BG100: 16.3 | BH100: 226.16K | BI100: -0.0908
B101: Mar 11 2024 | C101: 37.55 | D101: 37.55 | E101: 100 | F101: 37.55 | G101: Mar 11 2024 | H101: 7264343 | I101: 503700 | J101: 7264343 | M101: 45362 | N101: 37.55 | O101: 37.55 | P101: 37.55 | Q101: 37.55 | R101: 37.55 | S101: 100 | V101: 16-06-2024 | W101: 58.88 | X101: 61.9 | Y101: 61.9 | Z101: 56.01 | AA101: 19.28K | AB101: 0.0141 | AE101: 22-09-2024 | AF101: 84544.31 | AG101: 82985.33 | AH101: 84694.46 | AI101: 82700.63 | AJ101: 57.12M | AK101: 0.0199 | AM101: 29-09-2024 | AN101: 17.22 | AO101: 17.65 | AP101: 18.08 | AQ101: 16.72 | AR101: 455.14K | AS101: -0.0311 | AU101: 29-09-2024 | AV101: 65 | AW101: 68.25 | AX101: 70 | AY101: 63.05 | AZ101: 3.00K | BA101: 0 | BC101: 29-09-2024 | BD101: 18.72 | BE101: 18.77 | BF101: 20.64 | BG101: 17.72 | BH101: 511.82K | BI101: 0.0207
...

Sheet Guru BETA
B8: Regression Beta - 2 Years Monthly
B10: Guru Krupa Gems and Jewellery Ltd | F10: SENSEX Bse Return
B12: Date | C12: Close Price | D12: Return | F12: Date | G12: Close Price | H12: Return | J12: Beta Drafting | N12: SUMMARY OUTPUT
B13: 25-01-2026 | C13: 41.46 | F13: 25-01-2026 | G13: 82269.78
B14: 18-01-2026 | C14: 43.52 | D14: =C14/C13-1 -> 0.049686445 | F14: 18-01-2026 | G14: 81537.7 | H14: =G14/G13-1 -> -0.0088985287 | N14: Regression Statistics
B15: 46327 | C15: 42.87 | D15: =C15/C14-1 -> -0.014935662 | F15: 46327 | G15: 83570.35 | H15: =G15/G14-1 -> 0.024928959 | J15: Levered Raw Beta | K15: =O29 -> -0.033964804 | N15: Multiple R | O15: 0.0075600209
B16: 46113 | C16: 44.09 | D16: =C16/C15-1 -> 0.028458129 | F16: 46113 | G16: 83576.24 | H16: =G16/G15-1 -> 7.0479542e-05 | J16: Raw Beta Weight | K16: 0.75 | N16: R Square | O16: 5.7153917e-05
B17: 28-12-2025 | C17: 37.11 | D17: =C17/C16-1 -> -0.15831254 | F17: 28-12-2025 | G17: 85762.01 | H17: =G17/G16-1 -> 0.026153007 | N17: Adjusted R Square | O17: -0.0094661113
B18: 21-12-2025 | C18: 36.6 | D18: =C18/C17-1 -> -0.013742926 | F18: 21-12-2025 | G18: 85041.45 | H18: =G18/G17-1 -> -0.0084018553 | J18: Market Beta | K18: 1 | N18: Standard Error | O18: 0.074901478
B19: 14-12-2025 | C19: 32.19 | D19: =C19/C18-1 -> -0.1204918 | F19: 14-12-2025 | G19: 84929.36 | H19: =G19/G18-1 -> -0.0013180631 | J19: Market Beta Weight | K19: 0.25 | N19: Observations | O19: 107
B20: 45850 | C20: 28.43 | D20: =C20/C19-1 -> -0.11680646 | F20: 45850 | G20: 85267.66 | H20: =G20/G19-1 -> 0.0039833104
B21: 30-11-2025 | C21: 28.96 | D21: =C21/C20-1 -> 0.018642279 | F21: 30-11-2025 | G21: 85712.37 | H21: =G21/G20-1 -> 0.0052154592 | J21: Adjusted Beta | K21: =(K15*K16)+(K18*K19) -> 0.2245264 | N21: ANOVA
B22: 23-11-2025 | C22: 27.52 | D22: =C22/C21-1 -> -0.049723757 | F22: 23-11-2025 | G22: 85706.67 | H22: =G22/G21-1 -> -6.6501486e-05 | O22: df | P22: SS | Q22: MS | R22: F | S22: Significance F
B23: 16-11-2025 | C23: 26.19 | D23: =C23/C22-1 -> -0.048328488 | F23: 16-11-2025 | G23: 85231.92 | H23: =G23/G22-1 -> -0.0055392422 | N23: Regression | O23: 1 | P23: 3.3669828e-05 | Q23: 3.3669828e-05 | R23: 0.0060015043 | S23: 0.93839758
B24: 45911 | C24: 25.45 | D24: =C24/C23-1 -> -0.028255059 | F24: 45911 | G24: 84562.78 | H24: =G24/G23-1 -> -0.0078508146 | N24: Residual | O24: 105 | P24: 0.5890743 | Q24: 0.0056102314
B25: 45699 | C25: 24.92 | D25: =C25/C24-1 -> -0.020825147 | F25: 45699 | G25: 83216.28 | H25: =G25/G24-1 -> -0.015923081 | N25: Total | O25: 106 | P25: 0.58910797
B26: 26-10-2025 | C26: 23.97 | D26: =C26/C25-1 -> -0.03812199 | F26: 26-10-2025 | G26: 83938.71 | H26: =G26/G25-1 -> 0.0086813542
B27: 19-10-2025 | C27: 23.47 | D27: =C27/C26-1 -> -0.020859408 | F27: 19-10-2025 | G27: 84211.88 | H27: =G27/G26-1 -> 0.0032543984 | O27: Coefficients | P27: Standard Error | Q27: t Stat | R27: P-value | S27: Lower 95% | T27: Upper 95% | U27: Lower 95.0% | V27: Upper 95.0%
B28: 46001 | C28: 21.74 | D28: =C28/C27-1 -> -0.073711121 | F28: 46001 | G28: 83952.19 | H28: =G28/G27-1 -> -0.0030837692 | N28: Intercept | O28: -0.0039774271 | P28: 0.0072572163 | Q28: -0.54806512 | R28: 0.58481049 | S28: -0.018367146 | T28: 0.010412292 | U28: -0.018367146 | V28: 0.010412292
B29: 45787 | C29: 20.27 | D29: =C29/C28-1 -> -0.067617295 | F29: 45787 | G29: 82500.82 | H29: =G29/G28-1 -> -0.017288054 | N29: X Variable 1 | O29: -0.033964804 | P29: 0.43842878 | Q29: -0.077469376 | R29: 0.93839758 | S29: -0.90328808 | T29: 0.83535847 | U29: -0.90328808 | V29: 0.83535847
B30: 28-09-2025 | C30: 20.86 | D30: =C30/C29-1 -> 0.029107055 | F30: 28-09-2025 | G30: 81207.17 | H30: =G30/G29-1 -> -0.01568045
B31: 21-09-2025 | C31: 19.56 | D31: =C31/C30-1 -> -0.06232023 | F31: 21-09-2025 | G31: 80426.46 | H31: =G31/G30-1 -> -0.0096138063
B32: 14-09-2025 | C32: 21.12 | D32: =C32/C31-1 -> 0.079754601 | F32: 14-09-2025 | G32: 82626.23 | H32: =G32/G31-1 -> 0.027351322
B33: 45847 | C33: 21.14 | D33: =C33/C32-1 -> 0.0009469697 | F33: 45847 | G33: 81904.7 | H33: =G33/G32-1 -> -0.008732457
B34: 31-08-2025 | C34: 20.69 | D34: =C34/C33-1 -> -0.02128666 | F34: 31-08-2025 | G34: 80710.76 | H34: =G34/G33-1 -> -0.014577185
B35: 24-08-2025 | C35: 21.13 | D35: =C35/C34-1 -> 0.021266312 | F35: 24-08-2025 | G35: 79809.65 | H35: =G35/G34-1 -> -0.011164682
B36: 17-08-2025 | C36: 21.12 | D36: =C36/C35-1 -> -0.00047326077 | F36: 17-08-2025 | G36: 81306.85 | H36: =G36/G35-1 -> 0.018759636
B37: 45938 | C37: 20.16 | D37: =C37/C36-1 -> -0.045454545 | F37: 45938 | G37: 80597.66 | H37: =G37/G36-1 -> -0.0087223893
B38: 45724 | C38: 19.99 | D38: =C38/C37-1 -> -0.0084325397 | F38: 45724 | G38: 79857.79 | H38: =G38/G37-1 -> -0.009179795
B39: 27-07-2025 | C39: 20.21 | D39: =C39/C38-1 -> 0.011005503 | F39: 27-07-2025 | G39: 80599.91 | H39: =G39/G38-1 -> 0.0092930195
B40: 20-07-2025 | C40: 17.7 | D40: =C40/C39-1 -> -0.12419594 | F40: 20-07-2025 | G40: 81463.09 | H40: =G40/G39-1 -> 0.010709441
B41: 13-07-2025 | C41: 18.43 | D41: =C41/C40-1 -> 0.041242938 | F41: 13-07-2025 | G41: 81757.73 | H41: =G41/G40-1 -> 0.0036168527
B42: 45815 | C42: 16.97 | D42: =C42/C41-1 -> -0.079218665 | F42: 45815 | G42: 82500.47 | H42: =G42/G41-1 -> 0.0090846456
B43: 29-06-2025 | C43: 16.22 | D43: =C43/C42-1 -> -0.044195639 | F43: 29-06-2025 | G43: 83432.89 | H43: =G43/G42-1 -> 0.011301996
B44: 22-06-2025 | C44: 12.3 | D44: =C44/C43-1 -> -0.24167694 | F44: 22-06-2025 | G44: 84058.9 | H44: =G44/G43-1 -> 0.0075031561
B45: 15-06-2025 | C45: 12.29 | D45: =C45/C44-1 -> -0.00081300813 | F45: 15-06-2025 | G45: 82408.17 | H45: =G45/G44-1 -> -0.019637778
B46: 45875 | C46: 11.9 | D46: =C46/C45-1 -> -0.031733116 | F46: 45875 | G46: 81118.6 | H46: =G46/G45-1 -> -0.01564857
B47: 45663 | C47: 11.71 | D47: =C47/C46-1 -> -0.015966387 | F47: 45663 | G47: 82188.99 | H47: =G47/G46-1 -> 0.013195371
B48: 25-05-2025 | C48: 11.68 | D48: =C48/C47-1 -> -0.0025619129 | F48: 25-05-2025 | G48: 81451.01 | H48: =G48/G47-1 -> -0.0089790616
B49: 18-05-2025 | C49: 12.16 | D49: =C49/C48-1 -> 0.04109589 | F49: 18-05-2025 | G49: 81721.08 | H49: =G49/G48-1 -> 0.0033157354
B50: 45966 | C50: 12.25 | D50: =C50/C49-1 -> 0.0074013158 | F50: 45966 | G50: 82330.59 | H50: =G50/G49-1 -> 0.0074584183
B51: 45752 | C51: 10.94 | D51: =C51/C50-1 -> -0.10693878 | F51: 45752 | G51: 79454.47 | H51: =G51/G50-1 -> -0.034933796
B52: 27-04-2025 | C52: 11.47 | D52: =C52/C51-1 -> 0.048446069 | F52: 27-04-2025 | G52: 80501.99 | H52: =G52/G51-1 -> 0.013183903
B53: 20-04-2025 | C53: 11.9 | D53: =C53/C52-1 -> 0.037489102 | F53: 20-04-2025 | G53: 79212.53 | H53: =G53/G52-1 -> -0.016017741
B54: 13-04-2025 | C54: 12.49 | D54: =C54/C53-1 -> 0.049579832 | F54: 13-04-2025 | G54: 78553.2 | H54: =G54/G53-1 -> -0.0083235569
B55: 45812 | C55: 12.57 | D55: =C55/C54-1 -> 0.0064051241 | F55: 45812 | G55: 75157.26 | H55: =G55/G54-1 -> -0.043231084
B56: 30-03-2025 | C56: 13.73 | D56: =C56/C55-1 -> 0.092283214 | F56: 30-03-2025 | G56: 75364.69 | H56: =G56/G55-1 -> 0.0027599463
B57: 23-03-2025 | C57: 10.71 | D57: =C57/C56-1 -> -0.2199563 | F57: 23-03-2025 | G57: 77414.92 | H57: =G57/G56-1 -> 0.027204119
B58: 16-03-2025 | C58: 12.85 | D58: =C58/C57-1 -> 0.19981326 | F58: 16-03-2025 | G58: 76905.51 | H58: =G58/G57-1 -> -0.0065802561
B59: 45903 | C59: 12.84 | D59: =C59/C58-1 -> -0.00077821012 | F59: 45903 | G59: 73828.91 | H59: =G59/G58-1 -> -0.040004936
B60: 45691 | C60: 13.94 | D60: =C60/C59-1 -> 0.085669782 | F60: 45691 | G60: 74332.58 | H60: =G60/G59-1 -> 0.0068221243
B61: 23-02-2025 | C61: 13.58 | D61: =C61/C60-1 -> -0.025824964 | F61: 23-02-2025 | G61: 73198.1 | H61: =G61/G60-1 -> -0.015262217
B62: 16-02-2025 | C62: 14.24 | D62: =C62/C61-1 -> 0.048600884 | F62: 16-02-2025 | G62: 75311.06 | H62: =G62/G61-1 -> 0.028866323
B63: 45902 | C63: 14.83 | D63: =C63/C62-1 -> 0.041432584 | F63: 45902 | G63: 75939.21 | H63: =G63/G62-1 -> 0.0083407404
B64: 45690 | C64: 15.04 | D64: =C64/C63-1 -> 0.014160486 | F64: 45690 | G64: 77860.19 | H64: =G64/G63-1 -> 0.025296286
B65: 26-01-2025 | C65: 15.24 | D65: =C65/C64-1 -> 0.013297872 | F65: 26-01-2025 | G65: 76190.46 | H65: =G65/G64-1 -> -0.021445234
B66: 19-01-2025 | C66: 14.26 | D66: =C66/C65-1 -> -0.064304462 | F66: 19-01-2025 | G66: 76619.33 | H66: =G66/G65-1 -> 0.0056289199
B67: 45992 | C67: 14.44 | D67: =C67/C66-1 -> 0.012622721 | F67: 45992 | G67: 77378.91 | H67: =G67/G66-1 -> 0.0099136863
B68: 45778 | C68: 14.05 | D68: =C68/C67-1 -> -0.02700831 | F68: 45778 | G68: 79223.11 | H68: =G68/G67-1 -> 0.023833368
B69: 29-12-2024 | C69: 14.72 | D69: =C69/C68-1 -> 0.047686833 | F69: 29-12-2024 | G69: 78699.07 | H69: =G69/G68-1 -> -0.0066147365
B70: 22-12-2024 | C70: 15.12 | D70: =C70/C69-1 -> 0.027173913 | F70: 22-12-2024 | G70: 78041.59 | H70: =G70/G69-1 -> -0.0083543554
B71: 15-12-2024 | C71: 15.58 | D71: =C71/C70-1 -> 0.03042328 | F71: 15-12-2024 | G71: 82133.12 | H71: =G71/G70-1 -> 0.052427558
B72: 45516 | C72: 15.97 | D72: =C72/C71-1 -> 0.025032092 | F72: 45516 | G72: 81709.12 | H72: =G72/G71-1 -> -0.0051623511
B73: 45303 | C73: 15.87 | D73: =C73/C72-1 -> -0.0062617408 | F73: 45303 | G73: 79802.79 | H73: =G73/G72-1 -> -0.023330688
B74: 24-11-2024 | C74: 15.95 | D74: =C74/C73-1 -> 0.0050409578 | F74: 24-11-2024 | G74: 79117.11 | H74: =G74/G73-1 -> -0.0085921808
B75: 17-11-2024 | C75: 15.13 | D75: =C75/C74-1 -> -0.051410658 | F75: 17-11-2024 | G75: 77580.31 | H75: =G75/G74-1 -> -0.01942437
B76: 45576 | C76: 14.6 | D76: =C76/C75-1 -> -0.035029742 | F76: 45576 | G76: 79486.32 | H76: =G76/G75-1 -> 0.024568218
B77: 45362 | C77: 16.35 | D77: =C77/C76-1 -> 0.11986301 | F77: 45362 | G77: 79724.12 | H77: =G77/G76-1 -> 0.0029917098
B78: 27-10-2024 | C78: 16.63 | D78: =C78/C77-1 -> 0.017125382 | F78: 27-10-2024 | G78: 79402.29 | H78: =G78/G77-1 -> -0.0040367959
B79: 20-10-2024 | C79: 15.95 | D79: =C79/C78-1 -> -0.040889958 | F79: 20-10-2024 | G79: 81224.75 | H79: =G79/G78-1 -> 0.022952235
B80: 13-10-2024 | C80: 17.17 | D80: =C80/C79-1 -> 0.076489028 | F80: 13-10-2024 | G80: 81381.36 | H80: =G80/G79-1 -> 0.0019281069
B81: 45453 | C81: 17.02 | D81: =C81/C80-1 -> -0.0087361677 | F81: 45453 | G81: 81688.45 | H81: =G81/G80-1 -> 0.0037734685
B82: 29-09-2024 | C82: 18.72 | D82: =C82/C81-1 -> 0.099882491 | F82: 29-09-2024 | G82: 85571.85 | H82: =G82/G81-1 -> 0.047539156
B83: 22-09-2024 | C83: 18.34 | D83: =C83/C82-1 -> -0.020299145 | F83: 22-09-2024 | G83: 84544.31 | H83: =G83/G82-1 -> -0.012007921
B84: 15-09-2024 | C84: 17.76 | D84: =C84/C83-1 -> -0.031624864 | F84: 15-09-2024 | G84: 82890.94 | H84: =G84/G83-1 -> -0.019556254
B85: 45513 | C85: 17.9 | D85: =C85/C84-1 -> 0.0078828829 | F85: 45513 | G85: 81183.93 | H85: =G85/G84-1 -> -0.020593445
B86: 45300 | C86: 16.45 | D86: =C86/C85-1 -> -0.081005587 | F86: 45300 | G86: 82365.77 | H86: =G86/G85-1 -> 0.014557561
B87: 25-08-2024 | C87: 17.18 | D87: =C87/C86-1 -> 0.0443769 | F87: 25-08-2024 | G87: 81086.21 | H87: =G87/G86-1 -> -0.015535094
B88: 18-08-2024 | C88: 17.35 | D88: =C88/C87-1 -> 0.009895227 | F88: 18-08-2024 | G88: 80436.84 | H88: =G88/G87-1 -> -0.0080083901
B89: 45604 | C89: 15.98 | D89: =C89/C88-1 -> -0.078962536 | F89: 45604 | G89: 79705.91 | H89: =G89/G88-1 -> -0.0090870054
B90: 45390 | C90: 17.07 | D90: =C90/C89-1 -> 0.068210263 | F90: 45390 | G90: 80981.95 | H90: =G90/G89-1 -> 0.016009352
B91: 28-07-2024 | C91: 17.11 | D91: =C91/C90-1 -> 0.0023432923 | F91: 28-07-2024 | G91: 81332.72 | H91: =G91/G90-1 -> 0.004331459
B92: 21-07-2024 | C92: 17.42 | D92: =C92/C91-1 -> 0.01811806 | F92: 21-07-2024 | G92: 80604.65 | H92: =G92/G91-1 -> -0.0089517478
B93: 14-07-2024 | C93: 16.48 | D93: =C93/C92-1 -> -0.053960964 | F93: 14-07-2024 | G93: 80519.34 | H93: =G93/G92-1 -> -0.0010583757
B94: 45480 | C94: 16.66 | D94: =C94/C93-1 -> 0.01092233 | F94: 45480 | G94: 79996.6 | H94: =G94/G93-1 -> -0.0064921049
B95: 30-06-2024 | C95: 17.4 | D95: =C95/C94-1 -> 0.044417767 | F95: 30-06-2024 | G95: 79032.73 | H95: =G95/G94-1 -> -0.012048887
B96: 23-06-2024 | C96: 17.49 | D96: =C96/C95-1 -> 0.0051724138 | F96: 23-06-2024 | G96: 77209.9 | H96: =G96/G95-1 -> -0.023064242
B97: 16-06-2024 | C97: 16.37 | D97: =C97/C96-1 -> -0.064036592 | F97: 16-06-2024 | G97: 76992.77 | H97: =G97/G96-1 -> -0.0028122041
B98: 45541 | C98: 16.56 | D98: =C98/C97-1 -> 0.011606597 | F98: 45541 | G98: 76693.36 | H98: =G98/G97-1 -> -0.0038888067
B99: 45328 | C99: 16.91 | D99: =C99/C98-1 -> 0.021135266 | F99: 45328 | G99: 73961.31 | H99: =G99/G98-1 -> -0.035623032
B100: 26-05-2024 | C100: 16.67 | D100: =C100/C99-1 -> -0.014192785 | F100: 26-05-2024 | G100: 75410.39 | H100: =G100/G99-1 -> 0.019592406
B101: 19-05-2024 | C101: 17.23 | D101: =C101/C100-1 -> 0.033593281 | F101: 19-05-2024 | G101: 74005.94 | H101: =G101/G100-1 -> -0.018624091
B102: 45631 | C102: 17.54 | D102: =C102/C101-1 -> 0.017991875 | F102: 45631 | G102: 72664.47 | H102: =G102/G101-1 -> -0.018126518
B103: 45417 | C103: 17.96 | D103: =C103/C102-1 -> 0.023945268 | F103: 45417 | G103: 73878.15 | H103: =G103/G102-1 -> 0.016702523
B104: 28-04-2024 | C104: 18.19 | D104: =C104/C103-1 -> 0.012806236 | F104: 28-04-2024 | G104: 73730.16 | H104: =G104/G103-1 -> -0.0020031633
B105: 21-04-2024 | C105: 18.49 | D105: =C105/C104-1 -> 0.016492578 | F105: 21-04-2024 | G105: 73088.33 | H105: =G105/G104-1 -> -0.0087051215
B106: 14-04-2024 | C106: 19.21 | D106: =C106/C105-1 -> 0.038939968 | F106: 14-04-2024 | G106: 74244.9 | H106: =G106/G105-1 -> 0.015824277
B107: 45477 | C107: 18.67 | D107: =C107/C106-1 -> -0.028110359 | F107: 45477 | G107: 74248.22 | H107: =G107/G106-1 -> 4.4716876e-05
B108: 31-03-2024 | C108: 21.81 | D108: =C108/C107-1 -> 0.16818425 | F108: 31-03-2024 | G108: 73651.35 | H108: =G108/G107-1 -> -0.0080388459
B109: 24-03-2024 | C109: 13.83 | D109: =C109/C108-1 -> -0.36588721 | F109: 24-03-2024 | G109: 72831.94 | H109: =G109/G108-1 -> -0.011125526
...

Sheet Mishka Exim Ltd
A8: Regression Beta - 2 Years Monthly
A10: Mishka Exim Ltd | E10: SENSEX Bse Return
M11: SUMMARY OUTPUT
A12: Date | B12: Close Price | C12: Return | E12: Date | F12: Close Price | G12: Return | I12: Beta Drafting
A13: 25-01-2026 | B13: 40.7 | E13: 25-01-2026 | F13: 82269.78 | M13: Regression Statistics
A14: 18-01-2026 | B14: 43.95 | C14: =B14/B13-1 -> 0.07985258 | E14: 18-01-2026 | F14: 81537.7 | G14: =F14/F13-1 -> -0.0088985287 | M14: Multiple R | N14: 0.15973607
A15: 46327 | B15: 44.2 | C15: =B15/B14-1 -> 0.0056882821 | E15: 46327 | F15: 83570.35 | G15: =F15/F14-1 -> 0.024928959 | I15: Levered Raw Beta | J15: =N28 -> 0.69271189 | M15: R Square | N15: 0.025515613
A16: 46113 | B16: 40 | C16: =B16/B15-1 -> -0.095022624 | E16: 46113 | F16: 83576.24 | G16: =F16/F15-1 -> 7.0479542e-05 | I16: Raw Beta Weight | J16: 0.75 | M16: Adjusted R Square | N16: 0.016234809
A17: 28-12-2025 | B17: 41.75 | C17: =B17/B16-1 -> 0.04375 | E17: 28-12-2025 | F17: 85762.01 | G17: =F17/F16-1 -> 0.026153007 | M17: Standard Error | N17: 0.071372971
A18: 21-12-2025 | B18: 40.04 | C18: =B18/B17-1 -> -0.040958084 | E18: 21-12-2025 | F18: 85041.45 | G18: =F18/F17-1 -> -0.0084018553 | I18: Market Beta | J18: 1 | M18: Observations | N18: 107
A19: 14-12-2025 | B19: 44.49 | C19: =B19/B18-1 -> 0.11113886 | E19: 14-12-2025 | F19: 84929.36 | G19: =F19/F18-1 -> -0.0013180631 | I19: Market Beta Weight | J19: 0.25
A20: 45850 | B20: 45.01 | C20: =B20/B19-1 -> 0.01168802 | E20: 45850 | F20: 85267.66 | G20: =F20/F19-1 -> 0.0039833104 | M20: ANOVA
A21: 30-11-2025 | B21: 46.99 | C21: =B21/B20-1 -> 0.043990224 | E21: 30-11-2025 | F21: 85712.37 | G21: =F21/F20-1 -> 0.0052154592 | I21: Adjusted Beta | J21: =(J15*J16)+(J18*J19) -> 0.76953392 | N21: df | O21: SS | P21: MS | Q21: F | R21: Significance F
A22: 23-11-2025 | B22: 46.9 | C22: =B22/B21-1 -> -0.0019153011 | E22: 23-11-2025 | F22: 85706.67 | G22: =F22/F21-1 -> -6.6501486e-05 | M22: Regression | N22: 1 | O22: 0.014005156 | P22: 0.014005156 | Q22: 2.7492891 | R22: 0.10028235
A23: 16-11-2025 | B23: 46.82 | C23: =B23/B22-1 -> -0.0017057569 | E23: 16-11-2025 | F23: 85231.92 | G23: =F23/F22-1 -> -0.0055392422 | M23: Residual | N23: 105 | O23: 0.5348806 | P23: 0.005094101
A24: 45911 | B24: 44.88 | C24: =B24/B23-1 -> -0.041435284 | E24: 45911 | F24: 84562.78 | G24: =F24/F23-1 -> -0.0078508146 | M24: Total | N24: 106 | O24: 0.54888576
A25: 45699 | B25: 46.86 | C25: =B25/B24-1 -> 0.044117647 | E25: 45699 | F25: 83216.28 | G25: =F25/F24-1 -> -0.015923081
A26: 26-10-2025 | B26: 38.56 | C26: =B26/B25-1 -> -0.17712335 | E26: 26-10-2025 | F26: 83938.71 | G26: =F26/F25-1 -> 0.0086813542 | N26: Coefficients | O26: Standard Error | P26: t Stat | Q26: P-value | R26: Lower 95% | S26: Upper 95% | T26: Lower 95.0% | U26: Upper 95.0%
A27: 19-10-2025 | B27: 37.09 | C27: =B27/B26-1 -> -0.038122407 | E27: 19-10-2025 | F27: 84211.88 | G27: =F27/F26-1 -> 0.0032543984 | M27: Intercept | N27: 0.002053945 | O27: 0.0069153387 | P27: 0.29701294 | Q27: 0.7670434 | R27: -0.011657894 | S27: 0.015765784 | T27: -0.011657894 | U27: 0.015765784
A28: 46001 | B28: 36.64 | C28: =B28/B27-1 -> -0.01213265 | E28: 46001 | F28: 83952.19 | G28: =F28/F27-1 -> -0.0030837692 | M28: X Variable 1 | N28: 0.69271189 | O28: 0.41777499 | P28: 1.658098 | Q28: 0.10028235 | R28: -0.13565874 | S28: 1.5210825 | T28: -0.13565874 | U28: 1.5210825
A29: 45787 | B29: 36 | C29: =B29/B28-1 -> -0.017467249 | E29: 45787 | F29: 82500.82 | G29: =F29/F28-1 -> -0.017288054
A30: 28-09-2025 | B30: 35 | C30: =B30/B29-1 -> -0.027777778 | E30: 28-09-2025 | F30: 81207.17 | G30: =F30/F29-1 -> -0.01568045
A31: 21-09-2025 | B31: 36.23 | C31: =B31/B30-1 -> 0.035142857 | E31: 21-09-2025 | F31: 80426.46 | G31: =F31/F30-1 -> -0.0096138063
A32: 14-09-2025 | B32: 38 | C32: =B32/B31-1 -> 0.04885454 | E32: 14-09-2025 | F32: 82626.23 | G32: =F32/F31-1 -> 0.027351322
A33: 45847 | B33: 38.08 | C33: =B33/B32-1 -> 0.0021052632 | E33: 45847 | F33: 81904.7 | G33: =F33/F32-1 -> -0.008732457
A34: 31-08-2025 | B34: 36.5 | C34: =B34/B33-1 -> -0.041491597 | E34: 31-08-2025 | F34: 80710.76 | G34: =F34/F33-1 -> -0.014577185
A35: 24-08-2025 | B35: 35.86 | C35: =B35/B34-1 -> -0.017534247 | E35: 24-08-2025 | F35: 79809.65 | G35: =F35/F34-1 -> -0.011164682
A36: 17-08-2025 | B36: 35.66 | C36: =B36/B35-1 -> -0.0055772448 | E36: 17-08-2025 | F36: 81306.85 | G36: =F36/F35-1 -> 0.018759636
A37: 45938 | B37: 35.21 | C37: =B37/B36-1 -> -0.012619181 | E37: 45938 | F37: 80597.66 | G37: =F37/F36-1 -> -0.0087223893
A38: 45724 | B38: 33.62 | C38: =B38/B37-1 -> -0.045157626 | E38: 45724 | F38: 79857.79 | G38: =F38/F37-1 -> -0.009179795
A39: 27-07-2025 | B39: 37.99 | C39: =B39/B38-1 -> 0.12998215 | E39: 27-07-2025 | F39: 80599.91 | G39: =F39/F38-1 -> 0.0092930195
A40: 20-07-2025 | B40: 44.56 | C40: =B40/B39-1 -> 0.17294025 | E40: 20-07-2025 | F40: 81463.09 | G40: =F40/F39-1 -> 0.010709441
A41: 13-07-2025 | B41: 39.09 | C41: =B41/B40-1 -> -0.12275583 | E41: 13-07-2025 | F41: 81757.73 | G41: =F41/F40-1 -> 0.0036168527
A42: 45815 | B42: 28.39 | C42: =B42/B41-1 -> -0.2737273 | E42: 45815 | F42: 82500.47 | G42: =F42/F41-1 -> 0.0090846456
A43: 29-06-2025 | B43: 26.37 | C43: =B43/B42-1 -> -0.071151814 | E43: 29-06-2025 | F43: 83432.89 | G43: =F43/F42-1 -> 0.011301996
A44: 22-06-2025 | B44: 27.98 | C44: =B44/B43-1 -> 0.061054228 | E44: 22-06-2025 | F44: 84058.9 | G44: =F44/F43-1 -> 0.0075031561
A45: 15-06-2025 | B45: 27.03 | C45: =B45/B44-1 -> -0.033952823 | E45: 15-06-2025 | F45: 82408.17 | G45: =F45/F44-1 -> -0.019637778
A46: 45875 | B46: 28.43 | C46: =B46/B45-1 -> 0.051794303 | E46: 45875 | F46: 81118.6 | G46: =F46/F45-1 -> -0.01564857
A47: 45663 | B47: 26 | C47: =B47/B46-1 -> -0.085473092 | E47: 45663 | F47: 82188.99 | G47: =F47/F46-1 -> 0.013195371
A48: 25-05-2025 | B48: 25.09 | C48: =B48/B47-1 -> -0.035 | E48: 25-05-2025 | F48: 81451.01 | G48: =F48/F47-1 -> -0.0089790616
A49: 18-05-2025 | B49: 25 | C49: =B49/B48-1 -> -0.0035870865 | E49: 18-05-2025 | F49: 81721.08 | G49: =F49/F48-1 -> 0.0033157354
A50: 45966 | B50: 25.45 | C50: =B50/B49-1 -> 0.018 | E50: 45966 | F50: 82330.59 | G50: =F50/F49-1 -> 0.0074584183
A51: 45752 | B51: 25.3 | C51: =B51/B50-1 -> -0.0058939096 | E51: 45752 | F51: 79454.47 | G51: =F51/F50-1 -> -0.034933796
A52: 27-04-2025 | B52: 25.3 | C52: =B52/B51-1 -> 0 | E52: 27-04-2025 | F52: 80501.99 | G52: =F52/F51-1 -> 0.013183903
A53: 20-04-2025 | B53: 25.25 | C53: =B53/B52-1 -> -0.0019762846 | E53: 20-04-2025 | F53: 79212.53 | G53: =F53/F52-1 -> -0.016017741
A54: 13-04-2025 | B54: 25.5 | C54: =B54/B53-1 -> 0.0099009901 | E54: 13-04-2025 | F54: 78553.2 | G54: =F54/F53-1 -> -0.0083235569
A55: 45812 | B55: 25.43 | C55: =B55/B54-1 -> -0.002745098 | E55: 45812 | F55: 75157.26 | G55: =F55/F54-1 -> -0.043231084
A56: 30-03-2025 | B56: 25.49 | C56: =B56/B55-1 -> 0.002359418 | E56: 30-03-2025 | F56: 75364.69 | G56: =F56/F55-1 -> 0.0027599463
A57: 23-03-2025 | B57: 25.3 | C57: =B57/B56-1 -> -0.0074539035 | E57: 23-03-2025 | F57: 77414.92 | G57: =F57/F56-1 -> 0.027204119
A58: 16-03-2025 | B58: 25.5 | C58: =B58/B57-1 -> 0.0079051383 | E58: 16-03-2025 | F58: 76905.51 | G58: =F58/F57-1 -> -0.0065802561
A59: 45903 | B59: 25.5 | C59: =B59/B58-1 -> 0 | E59: 45903 | F59: 73828.91 | G59: =F59/F58-1 -> -0.040004936
A60: 45691 | B60: 25.33 | C60: =B60/B59-1 -> -0.0066666667 | E60: 45691 | F60: 74332.58 | G60: =F60/F59-1 -> 0.0068221243
A61: 23-02-2025 | B61: 25.45 | C61: =B61/B60-1 -> 0.0047374655 | E61: 23-02-2025 | F61: 73198.1 | G61: =F61/F60-1 -> -0.015262217
A62: 16-02-2025 | B62: 25.41 | C62: =B62/B61-1 -> -0.0015717092 | E62: 16-02-2025 | F62: 75311.06 | G62: =F62/F61-1 -> 0.028866323
A63: 45902 | B63: 25.5 | C63: =B63/B62-1 -> 0.0035419126 | E63: 45902 | F63: 75939.21 | G63: =F63/F62-1 -> 0.0083407404
A64: 45690 | B64: 25.35 | C64: =B64/B63-1 -> -0.0058823529 | E64: 45690 | F64: 77860.19 | G64: =F64/F63-1 -> 0.025296286
A65: 26-01-2025 | B65: 25.2 | C65: =B65/B64-1 -> -0.0059171598 | E65: 26-01-2025 | F65: 76190.46 | G65: =F65/F64-1 -> -0.021445234
A66: 19-01-2025 | B66: 30.1 | C66: =B66/B65-1 -> 0.19444444 | E66: 19-01-2025 | F66: 76619.33 | G66: =F66/F65-1 -> 0.0056289199
A67: 45992 | B67: 36.09 | C67: =B67/B66-1 -> 0.19900332 | E67: 45992 | F67: 77378.91 | G67: =F67/F66-1 -> 0.0099136863
A68: 45778 | B68: 41.44 | C68: =B68/B67-1 -> 0.14824051 | E68: 45778 | F68: 79223.11 | G68: =F68/F67-1 -> 0.023833368
A69: 29-12-2024 | B69: 48.5 | C69: =B69/B68-1 -> 0.1703668 | E69: 29-12-2024 | F69: 78699.07 | G69: =F69/F68-1 -> -0.0066147365
A70: 22-12-2024 | B70: 57.5 | C70: =B70/B69-1 -> 0.18556701 | E70: 22-12-2024 | F70: 78041.59 | G70: =F70/F69-1 -> -0.0083543554
A71: 15-12-2024 | B71: 67 | C71: =B71/B70-1 -> 0.16521739 | E71: 15-12-2024 | F71: 82133.12 | G71: =F71/F70-1 -> 0.052427558
A72: 45516 | B72: 67.5 | C72: =B72/B71-1 -> 0.0074626866 | E72: 45516 | F72: 81709.12 | G72: =F72/F71-1 -> -0.0051623511
A73: 45303 | B73: 62.45 | C73: =B73/B72-1 -> -0.074814815 | E73: 45303 | F73: 79802.79 | G73: =F73/F72-1 -> -0.023330688
A74: 24-11-2024 | B74: 62.1 | C74: =B74/B73-1 -> -0.0056044836 | E74: 24-11-2024 | F74: 79117.11 | G74: =F74/F73-1 -> -0.0085921808
A75: 17-11-2024 | B75: 62.4 | C75: =B75/B74-1 -> 0.0048309179 | E75: 17-11-2024 | F75: 77580.31 | G75: =F75/F74-1 -> -0.01942437
A76: 45576 | B76: 62.5 | C76: =B76/B75-1 -> 0.0016025641 | E76: 45576 | F76: 79486.32 | G76: =F76/F75-1 -> 0.024568218
A77: 45362 | B77: 62.8 | C77: =B77/B76-1 -> 0.0048 | E77: 45362 | F77: 79724.12 | G77: =F77/F76-1 -> 0.0029917098
A78: 27-10-2024 | B78: 63.11 | C78: =B78/B77-1 -> 0.0049363057 | E78: 27-10-2024 | F78: 79402.29 | G78: =F78/F77-1 -> -0.0040367959
A79: 20-10-2024 | B79: 63.05 | C79: =B79/B78-1 -> -0.00095072096 | E79: 20-10-2024 | F79: 81224.75 | G79: =F79/F78-1 -> 0.022952235
A80: 13-10-2024 | B80: 62.95 | C80: =B80/B79-1 -> -0.0015860428 | E80: 13-10-2024 | F80: 81381.36 | G80: =F80/F79-1 -> 0.0019281069
A81: 45453 | B81: 64 | C81: =B81/B80-1 -> 0.016679905 | E81: 45453 | F81: 81688.45 | G81: =F81/F80-1 -> 0.0037734685
A82: 29-09-2024 | B82: 65 | C82: =B82/B81-1 -> 0.015625 | E82: 29-09-2024 | F82: 85571.85 | G82: =F82/F81-1 -> 0.047539156
A83: 22-09-2024 | B83: 65 | C83: =B83/B82-1 -> 0 | E83: 22-09-2024 | F83: 84544.31 | G83: =F83/F82-1 -> -0.012007921
A84: 15-09-2024 | B84: 60.75 | C84: =B84/B83-1 -> -0.065384615 | E84: 15-09-2024 | F84: 82890.94 | G84: =F84/F83-1 -> -0.019556254
A85: 45513 | B85: 58.66 | C85: =B85/B84-1 -> -0.034403292 | E85: 45513 | F85: 81183.93 | G85: =F85/F84-1 -> -0.020593445
A86: 45300 | B86: 59.58 | C86: =B86/B85-1 -> 0.0156836 | E86: 45300 | F86: 82365.77 | G86: =F86/F85-1 -> 0.014557561
A87: 25-08-2024 | B87: 55.59 | C87: =B87/B86-1 -> -0.066968781 | E87: 25-08-2024 | F87: 81086.21 | G87: =F87/F86-1 -> -0.015535094
A88: 18-08-2024 | B88: 43 | C88: =B88/B87-1 -> -0.22647958 | E88: 18-08-2024 | F88: 80436.84 | G88: =F88/F87-1 -> -0.0080083901
A89: 45604 | B89: 39.71 | C89: =B89/B88-1 -> -0.076511628 | E89: 45604 | F89: 79705.91 | G89: =F89/F88-1 -> -0.0090870054
A90: 45390 | B90: 36.15 | C90: =B90/B89-1 -> -0.089649962 | E90: 45390 | F90: 80981.95 | G90: =F90/F89-1 -> 0.016009352
A91: 28-07-2024 | B91: 36.08 | C91: =B91/B90-1 -> -0.0019363762 | E91: 28-07-2024 | F91: 81332.72 | G91: =F91/F90-1 -> 0.004331459
A92: 21-07-2024 | B92: 35.9 | C92: =B92/B91-1 -> -0.0049889135 | E92: 21-07-2024 | F92: 80604.65 | G92: =F92/F91-1 -> -0.0089517478
A93: 14-07-2024 | B93: 36.75 | C93: =B93/B92-1 -> 0.02367688 | E93: 14-07-2024 | F93: 80519.34 | G93: =F93/F92-1 -> -0.0010583757
A94: 45480 | B94: 34.75 | C94: =B94/B93-1 -> -0.054421769 | E94: 45480 | F94: 79996.6 | G94: =F94/F93-1 -> -0.0064921049
A95: 30-06-2024 | B95: 36.55 | C95: =B95/B94-1 -> 0.051798561 | E95: 30-06-2024 | F95: 79032.73 | G95: =F95/F94-1 -> -0.012048887
A96: 23-06-2024 | B96: 35.56 | C96: =B96/B95-1 -> -0.027086183 | E96: 23-06-2024 | F96: 77209.9 | G96: =F96/F95-1 -> -0.023064242
A97: 16-06-2024 | B97: 34.06 | C97: =B97/B96-1 -> -0.042182227 | E97: 16-06-2024 | F97: 76992.77 | G97: =F97/F96-1 -> -0.0028122041
A98: 45541 | B98: 37.76 | C98: =B98/B97-1 -> 0.10863183 | E98: 45541 | F98: 76693.36 | G98: =F98/F97-1 -> -0.0038888067
A99: 45328 | B99: 37.76 | C99: =B99/B98-1 -> 0 | E99: 45328 | F99: 73961.31 | G99: =F99/F98-1 -> -0.035623032
A100: 26-05-2024 | B100: 39.28 | C100: =B100/B99-1 -> 0.040254237 | E100: 26-05-2024 | F100: 75410.39 | G100: =F100/F99-1 -> 0.019592406
A101: 19-05-2024 | B101: 38.91 | C101: =B101/B100-1 -> -0.0094195519 | E101: 19-05-2024 | F101: 74005.94 | G101: =F101/F100-1 -> -0.018624091
A102: 45631 | B102: 39.49 | C102: =B102/B101-1 -> 0.014906194 | E102: 45631 | F102: 72664.47 | G102: =F102/F101-1 -> -0.018126518
A103: 45417 | B103: 39.95 | C103: =B103/B102-1 -> 0.011648519 | E103: 45417 | F103: 73878.15 | G103: =F103/F102-1 -> 0.016702523
A104: 28-04-2024 | B104: 37.82 | C104: =B104/B103-1 -> -0.053316646 | E104: 28-04-2024 | F104: 73730.16 | G104: =F104/F103-1 -> -0.0020031633
A105: 21-04-2024 | B105: 34.65 | C105: =B105/B104-1 -> -0.083818086 | E105: 21-04-2024 | F105: 73088.33 | G105: =F105/F104-1 -> -0.0087051215
A106: 14-04-2024 | B106: 34.01 | C106: =B106/B105-1 -> -0.018470418 | E106: 14-04-2024 | F106: 74244.9 | G106: =F106/F105-1 -> 0.015824277
A107: 45477 | B107: 35 | C107: =B107/B106-1 -> 0.029109086 | E107: 45477 | F107: 74248.22 | G107: =F107/F106-1 -> 4.4716876e-05
A108: 31-03-2024 | B108: 34.39 | C108: =B108/B107-1 -> -0.017428571 | E108: 31-03-2024 | F108: 73651.35 | G108: =F108/F107-1 -> -0.0080388459
...

Sheet Moksh BETA
A8: Regression Beta - 2 Years Monthly
A10: Moksh Ornaments Ltd | E10: SENSEX Bse Return
A12: Date | B12: Close Price | C12: Return | E12: Date | F12: Close Price | G12: Return | I12: Beta Drafting
A13: 25-01-2026 | B13: 13.75 | E13: 25-01-2026 | F13: 82269.78 | O13: SUMMARY OUTPUT
A14: 18-01-2026 | B14: 14.23 | C14: =B14/B13-1 -> 0.034909091 | E14: 18-01-2026 | F14: 81537.7 | G14: =F14/F13-1 -> -0.0088985287
A15: 46327 | B15: 14.75 | C15: =B15/B14-1 -> 0.036542516 | E15: 46327 | F15: 83570.35 | G15: =F15/F14-1 -> 0.024928959 | I15: Levered Raw Beta | J15: =P30 -> 0.58487445 | O15: Regression Statistics
A16: 46113 | B16: 15.02 | C16: =B16/B15-1 -> 0.018305085 | E16: 46113 | F16: 83576.24 | G16: =F16/F15-1 -> 7.0479542e-05 | I16: Raw Beta Weight | J16: 0.75 | O16: Multiple R | P16: 0.13665178
A17: 28-12-2025 | B17: 14.51 | C17: =B17/B16-1 -> -0.033954727 | E17: 28-12-2025 | F17: 85762.01 | G17: =F17/F16-1 -> 0.026153007 | O17: R Square | P17: 0.018673709
A18: 21-12-2025 | B18: 15.06 | C18: =B18/B17-1 -> 0.037904893 | E18: 21-12-2025 | F18: 85041.45 | G18: =F18/F17-1 -> -0.0084018553 | I18: Market Beta | J18: 1 | O18: Adjusted R Square | P18: 0.0093277444
A19: 14-12-2025 | B19: 15.32 | C19: =B19/B18-1 -> 0.017264276 | E19: 14-12-2025 | F19: 84929.36 | G19: =F19/F18-1 -> -0.0013180631 | I19: Market Beta Weight | J19: 0.25 | O19: Standard Error | P19: 0.070688824
A20: 45850 | B20: 14.07 | C20: =B20/B19-1 -> -0.081592689 | E20: 45850 | F20: 85267.66 | G20: =F20/F19-1 -> 0.0039833104 | O20: Observations | P20: 107
A21: 30-11-2025 | B21: 14.51 | C21: =B21/B20-1 -> 0.03127221 | E21: 30-11-2025 | F21: 85712.37 | G21: =F21/F20-1 -> 0.0052154592 | I21: Adjusted Beta | J21: =(J15*J16)+(J18*J19) -> 0.68865584
A22: 23-11-2025 | B22: 14.51 | C22: =B22/B21-1 -> 0 | E22: 23-11-2025 | F22: 85706.67 | G22: =F22/F21-1 -> -6.6501486e-05 | O22: ANOVA
A23: 16-11-2025 | B23: 13.25 | C23: =B23/B22-1 -> -0.086836664 | E23: 16-11-2025 | F23: 85231.92 | G23: =F23/F22-1 -> -0.0055392422 | P23: df | Q23: SS | R23: MS | S23: F | T23: Significance F
A24: 45911 | B24: 15.17 | C24: =B24/B23-1 -> 0.14490566 | E24: 45911 | F24: 84562.78 | G24: =F24/F23-1 -> -0.0078508146 | O24: Regression | P24: 1 | Q24: 0.0099840782 | R24: 0.0099840782 | S24: 1.9980505 | T24: 0.16045954
A25: 45699 | B25: 14.28 | C25: =B25/B24-1 -> -0.058668425 | E25: 45699 | F25: 83216.28 | G25: =F25/F24-1 -> -0.015923081 | O25: Residual | P25: 105 | Q25: 0.52467554 | R25: 0.0049969099
A26: 26-10-2025 | B26: 13.9 | C26: =B26/B25-1 -> -0.026610644 | E26: 26-10-2025 | F26: 83938.71 | G26: =F26/F25-1 -> 0.0086813542 | O26: Total | P26: 106 | Q26: 0.53465962
A27: 19-10-2025 | B27: 14.25 | C27: =B27/B26-1 -> 0.025179856 | E27: 19-10-2025 | F27: 84211.88 | G27: =F27/F26-1 -> 0.0032543984
A28: 46001 | B28: 14.3 | C28: =B28/B27-1 -> 0.0035087719 | E28: 46001 | F28: 83952.19 | G28: =F28/F27-1 -> -0.0030837692 | P28: Coefficients | Q28: Standard Error | R28: t Stat | S28: P-value | T28: Lower 95% | U28: Upper 95% | V28: Lower 95.0% | W28: Upper 95.0%
A29: 45787 | B29: 15.14 | C29: =B29/B28-1 -> 0.058741259 | E29: 45787 | F29: 82500.82 | G29: =F29/F28-1 -> -0.017288054 | O29: Intercept | P29: 0.002570253 | Q29: 0.0068490516 | R29: 0.37527137 | S29: 0.70821565 | T29: -0.011010151 | U29: 0.016150657 | V29: -0.011010151 | W29: 0.016150657
A30: 28-09-2025 | B30: 14.97 | C30: =B30/B29-1 -> -0.011228534 | E30: 28-09-2025 | F30: 81207.17 | G30: =F30/F29-1 -> -0.01568045 | O30: X Variable 1 | P30: 0.58487445 | Q30: 0.4137704 | R30: 1.4135241 | S30: 0.16045954 | T30: -0.23555583 | U30: 1.4053047 | V30: -0.23555583 | W30: 1.4053047
A31: 21-09-2025 | B31: 14.1 | C31: =B31/B30-1 -> -0.058116232 | E31: 21-09-2025 | F31: 80426.46 | G31: =F31/F30-1 -> -0.0096138063
A32: 14-09-2025 | B32: 14.8 | C32: =B32/B31-1 -> 0.04964539 | E32: 14-09-2025 | F32: 82626.23 | G32: =F32/F31-1 -> 0.027351322
A33: 45847 | B33: 13.89 | C33: =B33/B32-1 -> -0.061486486 | E33: 45847 | F33: 81904.7 | G33: =F33/F32-1 -> -0.008732457
A34: 31-08-2025 | B34: 13.9 | C34: =B34/B33-1 -> 0.0007199424 | E34: 31-08-2025 | F34: 80710.76 | G34: =F34/F33-1 -> -0.014577185
A35: 24-08-2025 | B35: 13.58 | C35: =B35/B34-1 -> -0.023021583 | E35: 24-08-2025 | F35: 79809.65 | G35: =F35/F34-1 -> -0.011164682
A36: 17-08-2025 | B36: 13.81 | C36: =B36/B35-1 -> 0.016936672 | E36: 17-08-2025 | F36: 81306.85 | G36: =F36/F35-1 -> 0.018759636
A37: 45938 | B37: 13.67 | C37: =B37/B36-1 -> -0.010137581 | E37: 45938 | F37: 80597.66 | G37: =F37/F36-1 -> -0.0087223893
A38: 45724 | B38: 13.74 | C38: =B38/B37-1 -> 0.0051207023 | E38: 45724 | F38: 79857.79 | G38: =F38/F37-1 -> -0.009179795
A39: 27-07-2025 | B39: 13.83 | C39: =B39/B38-1 -> 0.0065502183 | E39: 27-07-2025 | F39: 80599.91 | G39: =F39/F38-1 -> 0.0092930195
A40: 20-07-2025 | B40: 13.82 | C40: =B40/B39-1 -> -0.0007230658 | E40: 20-07-2025 | F40: 81463.09 | G40: =F40/F39-1 -> 0.010709441
A41: 13-07-2025 | B41: 14.57 | C41: =B41/B40-1 -> 0.054269175 | E41: 13-07-2025 | F41: 81757.73 | G41: =F41/F40-1 -> 0.0036168527
A42: 45815 | B42: 14.64 | C42: =B42/B41-1 -> 0.0048043926 | E42: 45815 | F42: 82500.47 | G42: =F42/F41-1 -> 0.0090846456
A43: 29-06-2025 | B43: 14.84 | C43: =B43/B42-1 -> 0.013661202 | E43: 29-06-2025 | F43: 83432.89 | G43: =F43/F42-1 -> 0.011301996
A44: 22-06-2025 | B44: 14.4 | C44: =B44/B43-1 -> -0.029649596 | E44: 22-06-2025 | F44: 84058.9 | G44: =F44/F43-1 -> 0.0075031561
A45: 15-06-2025 | B45: 14.71 | C45: =B45/B44-1 -> 0.021527778 | E45: 15-06-2025 | F45: 82408.17 | G45: =F45/F44-1 -> -0.019637778
A46: 45875 | B46: 14.84 | C46: =B46/B45-1 -> 0.0088375255 | E46: 45875 | F46: 81118.6 | G46: =F46/F45-1 -> -0.01564857
A47: 45663 | B47: 14.85 | C47: =B47/B46-1 -> 0.00067385445 | E47: 45663 | F47: 82188.99 | G47: =F47/F46-1 -> 0.013195371
A48: 25-05-2025 | B48: 15.11 | C48: =B48/B47-1 -> 0.017508418 | E48: 25-05-2025 | F48: 81451.01 | G48: =F48/F47-1 -> -0.0089790616
A49: 18-05-2025 | B49: 13.99 | C49: =B49/B48-1 -> -0.074123097 | E49: 18-05-2025 | F49: 81721.08 | G49: =F49/F48-1 -> 0.0033157354
A50: 45966 | B50: 14.13 | C50: =B50/B49-1 -> 0.010007148 | E50: 45966 | F50: 82330.59 | G50: =F50/F49-1 -> 0.0074584183
A51: 45752 | B51: 13.3 | C51: =B51/B50-1 -> -0.058740269 | E51: 45752 | F51: 79454.47 | G51: =F51/F50-1 -> -0.034933796
A52: 27-04-2025 | B52: 13.81 | C52: =B52/B51-1 -> 0.038345865 | E52: 27-04-2025 | F52: 80501.99 | G52: =F52/F51-1 -> 0.013183903
A53: 20-04-2025 | B53: 13.35 | C53: =B53/B52-1 -> -0.033309196 | E53: 20-04-2025 | F53: 79212.53 | G53: =F53/F52-1 -> -0.016017741
A54: 13-04-2025 | B54: 13.82 | C54: =B54/B53-1 -> 0.035205993 | E54: 13-04-2025 | F54: 78553.2 | G54: =F54/F53-1 -> -0.0083235569
A55: 45812 | B55: 14.36 | C55: =B55/B54-1 -> 0.039073806 | E55: 45812 | F55: 75157.26 | G55: =F55/F54-1 -> -0.043231084
A56: 30-03-2025 | B56: 14.44 | C56: =B56/B55-1 -> 0.0055710306 | E56: 30-03-2025 | F56: 75364.69 | G56: =F56/F55-1 -> 0.0027599463
A57: 23-03-2025 | B57: 13.33 | C57: =B57/B56-1 -> -0.076869806 | E57: 23-03-2025 | F57: 77414.92 | G57: =F57/F56-1 -> 0.027204119
A58: 16-03-2025 | B58: 14.38 | C58: =B58/B57-1 -> 0.078769692 | E58: 16-03-2025 | F58: 76905.51 | G58: =F58/F57-1 -> -0.0065802561
A59: 45903 | B59: 12.4 | C59: =B59/B58-1 -> -0.13769124 | E59: 45903 | F59: 73828.91 | G59: =F59/F58-1 -> -0.040004936
A60: 45691 | B60: 13.35 | C60: =B60/B59-1 -> 0.076612903 | E60: 45691 | F60: 74332.58 | G60: =F60/F59-1 -> 0.0068221243
A61: 23-02-2025 | B61: 12.76 | C61: =B61/B60-1 -> -0.044194757 | E61: 23-02-2025 | F61: 73198.1 | G61: =F61/F60-1 -> -0.015262217
A62: 16-02-2025 | B62: 13.32 | C62: =B62/B61-1 -> 0.043887147 | E62: 16-02-2025 | F62: 75311.06 | G62: =F62/F61-1 -> 0.028866323
A63: 45902 | B63: 12.93 | C63: =B63/B62-1 -> -0.029279279 | E63: 45902 | F63: 75939.21 | G63: =F63/F62-1 -> 0.0083407404
A64: 45690 | B64: 14.91 | C64: =B64/B63-1 -> 0.15313225 | E64: 45690 | F64: 77860.19 | G64: =F64/F63-1 -> 0.025296286
A65: 26-01-2025 | B65: 14.71 | C65: =B65/B64-1 -> -0.013413816 | E65: 26-01-2025 | F65: 76190.46 | G65: =F65/F64-1 -> -0.021445234
A66: 19-01-2025 | B66: 16.3 | C66: =B66/B65-1 -> 0.10808973 | E66: 19-01-2025 | F66: 76619.33 | G66: =F66/F65-1 -> 0.0056289199
A67: 45992 | B67: 18.24 | C67: =B67/B66-1 -> 0.1190184 | E67: 45992 | F67: 77378.91 | G67: =F67/F66-1 -> 0.0099136863
A68: 45778 | B68: 17.79 | C68: =B68/B67-1 -> -0.024671053 | E68: 45778 | F68: 79223.11 | G68: =F68/F67-1 -> 0.023833368
A69: 29-12-2024 | B69: 20.6 | C69: =B69/B68-1 -> 0.15795391 | E69: 29-12-2024 | F69: 78699.07 | G69: =F69/F68-1 -> -0.0066147365
A70: 22-12-2024 | B70: 19.19 | C70: =B70/B69-1 -> -0.068446602 | E70: 22-12-2024 | F70: 78041.59 | G70: =F70/F69-1 -> -0.0083543554
A71: 15-12-2024 | B71: 20.8 | C71: =B71/B70-1 -> 0.083897863 | E71: 15-12-2024 | F71: 82133.12 | G71: =F71/F70-1 -> 0.052427558
A72: 45516 | B72: 19.73 | C72: =B72/B71-1 -> -0.051442308 | E72: 45516 | F72: 81709.12 | G72: =F72/F71-1 -> -0.0051623511
A73: 45303 | B73: 16.82 | C73: =B73/B72-1 -> -0.14749113 | E73: 45303 | F73: 79802.79 | G73: =F73/F72-1 -> -0.023330688
A74: 24-11-2024 | B74: 16.42 | C74: =B74/B73-1 -> -0.023781213 | E74: 24-11-2024 | F74: 79117.11 | G74: =F74/F73-1 -> -0.0085921808
A75: 17-11-2024 | B75: 15.53 | C75: =B75/B74-1 -> -0.054202192 | E75: 17-11-2024 | F75: 77580.31 | G75: =F75/F74-1 -> -0.01942437
A76: 45576 | B76: 15.39 | C76: =B76/B75-1 -> -0.00901481 | E76: 45576 | F76: 79486.32 | G76: =F76/F75-1 -> 0.024568218
A77: 45362 | B77: 15.89 | C77: =B77/B76-1 -> 0.032488629 | E77: 45362 | F77: 79724.12 | G77: =F77/F76-1 -> 0.0029917098
A78: 27-10-2024 | B78: 16.67 | C78: =B78/B77-1 -> 0.049087476 | E78: 27-10-2024 | F78: 79402.29 | G78: =F78/F77-1 -> -0.0040367959
A79: 20-10-2024 | B79: 15.82 | C79: =B79/B78-1 -> -0.050989802 | E79: 20-10-2024 | F79: 81224.75 | G79: =F79/F78-1 -> 0.022952235
A80: 13-10-2024 | B80: 17.22 | C80: =B80/B79-1 -> 0.088495575 | E80: 13-10-2024 | F80: 81381.36 | G80: =F80/F79-1 -> 0.0019281069
A81: 45453 | B81: 18.42 | C81: =B81/B80-1 -> 0.069686411 | E81: 45453 | F81: 81688.45 | G81: =F81/F80-1 -> 0.0037734685
A82: 29-09-2024 | B82: 17.22 | C82: =B82/B81-1 -> -0.06514658 | E82: 29-09-2024 | F82: 85571.85 | G82: =F82/F81-1 -> 0.047539156
A83: 22-09-2024 | B83: 17.77 | C83: =B83/B82-1 -> 0.031939605 | E83: 22-09-2024 | F83: 84544.31 | G83: =F83/F82-1 -> -0.012007921
A84: 15-09-2024 | B84: 18.15 | C84: =B84/B83-1 -> 0.021384356 | E84: 15-09-2024 | F84: 82890.94 | G84: =F84/F83-1 -> -0.019556254
A85: 45513 | B85: 20.15 | C85: =B85/B84-1 -> 0.11019284 | E85: 45513 | F85: 81183.93 | G85: =F85/F84-1 -> -0.020593445
A86: 45300 | B86: 20.73 | C86: =B86/B85-1 -> 0.028784119 | E86: 45300 | F86: 82365.77 | G86: =F86/F85-1 -> 0.014557561
A87: 25-08-2024 | B87: 18.04 | C87: =B87/B86-1 -> -0.12976363 | E87: 25-08-2024 | F87: 81086.21 | G87: =F87/F86-1 -> -0.015535094
A88: 18-08-2024 | B88: 17.74 | C88: =B88/B87-1 -> -0.016629712 | E88: 18-08-2024 | F88: 80436.84 | G88: =F88/F87-1 -> -0.0080083901
A89: 45604 | B89: 16.61 | C89: =B89/B88-1 -> -0.063697858 | E89: 45604 | F89: 79705.91 | G89: =F89/F88-1 -> -0.0090870054
A90: 45390 | B90: 16.54 | C90: =B90/B89-1 -> -0.0042143287 | E90: 45390 | F90: 80981.95 | G90: =F90/F89-1 -> 0.016009352
A91: 28-07-2024 | B91: 15.27 | C91: =B91/B90-1 -> -0.076783555 | E91: 28-07-2024 | F91: 81332.72 | G91: =F91/F90-1 -> 0.004331459
A92: 21-07-2024 | B92: 15.78 | C92: =B92/B91-1 -> 0.033398821 | E92: 21-07-2024 | F92: 80604.65 | G92: =F92/F91-1 -> -0.0089517478
A93: 14-07-2024 | B93: 14.52 | C93: =B93/B92-1 -> -0.079847909 | E93: 14-07-2024 | F93: 80519.34 | G93: =F93/F92-1 -> -0.0010583757
A94: 45480 | B94: 13.03 | C94: =B94/B93-1 -> -0.10261708 | E94: 45480 | F94: 79996.6 | G94: =F94/F93-1 -> -0.0064921049
A95: 30-06-2024 | B95: 13.45 | C95: =B95/B94-1 -> 0.032233308 | E95: 30-06-2024 | F95: 79032.73 | G95: =F95/F94-1 -> -0.012048887
A96: 23-06-2024 | B96: 13.23 | C96: =B96/B95-1 -> -0.016356877 | E96: 23-06-2024 | F96: 77209.9 | G96: =F96/F95-1 -> -0.023064242
A97: 16-06-2024 | B97: 12.29 | C97: =B97/B96-1 -> -0.071050642 | E97: 16-06-2024 | F97: 76992.77 | G97: =F97/F96-1 -> -0.0028122041
A98: 45541 | B98: 13.05 | C98: =B98/B97-1 -> 0.061838893 | E98: 45541 | F98: 76693.36 | G98: =F98/F97-1 -> -0.0038888067
A99: 45328 | B99: 12.07 | C99: =B99/B98-1 -> -0.075095785 | E99: 45328 | F99: 73961.31 | G99: =F99/F98-1 -> -0.035623032
A100: 26-05-2024 | B100: 13.12 | C100: =B100/B99-1 -> 0.086992543 | E100: 26-05-2024 | F100: 75410.39 | G100: =F100/F99-1 -> 0.019592406
A101: 19-05-2024 | B101: 13.95 | C101: =B101/B100-1 -> 0.063262195 | E101: 19-05-2024 | F101: 74005.94 | G101: =F101/F100-1 -> -0.018624091
A102: 45631 | B102: 15.14 | C102: =B102/B101-1 -> 0.085304659 | E102: 45631 | F102: 72664.47 | G102: =F102/F101-1 -> -0.018126518
A103: 45417 | B103: 13.78 | C103: =B103/B102-1 -> -0.089828269 | E103: 45417 | F103: 73878.15 | G103: =F103/F102-1 -> 0.016702523
A104: 28-04-2024 | B104: 14.83 | C104: =B104/B103-1 -> 0.076197388 | E104: 28-04-2024 | F104: 73730.16 | G104: =F104/F103-1 -> -0.0020031633
A105: 21-04-2024 | B105: 14.74 | C105: =B105/B104-1 -> -0.0060687795 | E105: 21-04-2024 | F105: 73088.33 | G105: =F105/F104-1 -> -0.0087051215
A106: 14-04-2024 | B106: 15.18 | C106: =B106/B105-1 -> 0.029850746 | E106: 14-04-2024 | F106: 74244.9 | G106: =F106/F105-1 -> 0.015824277
A107: 45477 | B107: 16.37 | C107: =B107/B106-1 -> 0.078392622 | E107: 45477 | F107: 74248.22 | G107: =F107/F106-1 -> 4.4716876e-05
A108: 31-03-2024 | B108: 17.68 | C108: =B108/B107-1 -> 0.080024435 | E108: 31-03-2024 | F108: 73651.35 | G108: =F108/F107-1 -> -0.0080388459
A109: 24-03-2024 | B109: 14.96 | C109: =B109/B108-1 -> -0.15384615 | E109: 24-03-2024 | F109: 72831.94 | G109: =F109/F108-1 -> -0.011125526
...

Sheet beta sj corpoation
L3: 1
B6: Regression Beta - 2 Years Monthly
B8: SJ Corporation Ltd | F8: SENSEX Bse Return
R9: SUMMARY OUTPUT
B10: Date | C10: Close Price | D10: Return | F10: Date | G10: Close Price | H10: Return
B11: Jan 26 2026 | C11: 68.07 | F11: Jan 26 2026 | G11: 8226978 | K11: Beta Drafting | R11: Regression Statistics
B12: Jan 19 2026 | C12: 65 | D12: =C12/C11-1 -> -0.045100632 | F12: Jan 19 2026 | G12: 8153770 | H12: =G12/G11-1 -> -0.0088985287 | R12: Multiple R | S12: 0.1396718
B13: Jan 12 2026 | C13: 65 | D13: =C13/C12-1 -> 0 | F13: Jan 12 2026 | G13: 8357035 | H13: =G13/G12-1 -> 0.024928959 | R13: R Square | S13: 0.019508212
B14: Jan 5 2026 | C14: 65 | D14: =C14/C13-1 -> 0 | F14: Jan 5 2026 | G14: 8357624 | H14: =G14/G13-1 -> 7.0479542e-05 | K14: Levered Raw Beta | L14: =R29 -> -0.1905929 | R14: Adjusted R Square | S14: 0.01025829
B15: Dec 29 2025 | C15: 65 | D15: =C15/C14-1 -> 0 | F15: Dec 29 2025 | G15: 8576201 | H15: =G15/G14-1 -> 0.026153007 | K15: Raw Beta Weight | L15: 0.75 | R15: Standard Error | S15: 0.022355726
B16: Dec 22 2025 | C16: 65 | D16: =C16/C15-1 -> 0 | F16: Dec 22 2025 | G16: 8504145 | H16: =G16/G15-1 -> -0.0084018553 | R16: Observations | S16: 108
B17: Dec 15 2025 | C17: 65 | D17: =C17/C16-1 -> 0 | F17: Dec 15 2025 | G17: 8492936 | H17: =G17/G16-1 -> -0.0013180631 | K17: Market Beta | L17: 1
B18: Dec 8 2025 | C18: 65 | D18: =C18/C17-1 -> 0 | F18: Dec 8 2025 | G18: 8526766 | H18: =G18/G17-1 -> 0.0039833104 | K18: Market Beta Weight | L18: 0.25 | R18: ANOVA
B19: Dec 1 2025 | C19: 65 | D19: =C19/C18-1 -> 0 | F19: Dec 1 2025 | G19: 8571237 | H19: =G19/G18-1 -> 0.0052154592 | S19: df | T19: SS | U19: MS | V19: F | W19: Significance F
B20: Nov 24 2025 | C20: 65 | D20: =C20/C19-1 -> 0 | F20: Nov 24 2025 | G20: 8570667 | H20: =G20/G19-1 -> -6.6501486e-05 | K20: Adjusted Beta | L20: =(L14*L15)+(L17*L18) -> 0.10705532 | R20: Regression | S20: 1 | T20: 0.0010540396 | U20: 0.0010540396 | V20: 2.1090136 | W20: 0.14938731
B21: Nov 17 2025 | C21: 65 | D21: =C21/C20-1 -> 0 | F21: Nov 17 2025 | G21: 8523192 | H21: =G21/G20-1 -> -0.0055392422 | R21: Residual | S21: 106 | T21: 0.05297652 | U21: 0.00049977849
B22: Nov 10 2025 | C22: 65 | D22: =C22/C21-1 -> 0 | F22: Nov 10 2025 | G22: 8456278 | H22: =G22/G21-1 -> -0.0078508146 | R22: Total | S22: 107 | T22: 0.05403056
B23: Nov 3 2025 | C23: 65 | D23: =C23/C22-1 -> 0 | F23: Nov 3 2025 | G23: 8321628 | H23: =G23/G22-1 -> -0.015923081
B24: Oct 27 2025 | C24: 65 | D24: =C24/C23-1 -> 0 | F24: Oct 27 2025 | G24: 8393871 | H24: =G24/G23-1 -> 0.0086813542 | S24: Coefficients | T24: Standard Error | U24: t Stat | V24: P-value | W24: Lower 95% | X24: Upper 95% | Y24: Lower 95.0% | Z24: Upper 95.0%
B25: Oct 20 2025 | C25: 65 | D25: =C25/C24-1 -> 0 | F25: Oct 20 2025 | G25: 8421188 | H25: =G25/G24-1 -> 0.0032543984 | R25: Intercept | S25: -0.0049737563 | T25: 0.002155989 | U25: -2.3069488 | V25: 0.023001605 | W25: -0.0092482143 | X25: -0.00069929834 | Y25: -0.0092482143 | Z25: -0.00069929834
B26: Oct 13 2025 | C26: 64.97 | D26: =C26/C25-1 -> -0.00046153846 | F26: Oct 13 2025 | G26: 8395219 | H26: =G26/G25-1 -> -0.0030837692 | R26: X Variable 1 | S26: -0.1905929 | T26: 0.13124025 | U26: -1.4522443 | V26: 0.14938731 | W26: -0.45078946 | X26: 0.069603649 | Y26: -0.45078946 | Z26: 0.069603649
B27: Oct 6 2025 | C27: 64.97 | D27: =C27/C26-1 -> 0 | F27: Oct 6 2025 | G27: 8250082 | H27: =G27/G26-1 -> -0.017288054
B28: Sep 29 2025 | C28: 64.97 | D28: =C28/C27-1 -> 0 | F28: Sep 29 2025 | G28: 8120717 | H28: =G28/G27-1 -> -0.01568045
B29: Sep 22 2025 | C29: 64.97 | D29: =C29/C28-1 -> 0 | F29: Sep 22 2025 | G29: 8042646 | H29: =G29/G28-1 -> -0.0096138063 | R29: =S26 -> -0.1905929
B30: Sep 15 2025 | C30: 64.97 | D30: =C30/C29-1 -> 0 | F30: Sep 15 2025 | G30: 8262623 | H30: =G30/G29-1 -> 0.027351322
B31: Sep 8 2025 | C31: 64.97 | D31: =C31/C30-1 -> 0 | F31: Sep 8 2025 | G31: 8190470 | H31: =G31/G30-1 -> -0.008732457
B32: Sep 1 2025 | C32: 64.97 | D32: =C32/C31-1 -> 0 | F32: Sep 1 2025 | G32: 8071076 | H32: =G32/G31-1 -> -0.014577185
B33: Aug 25 2025 | C33: 64.97 | D33: =C33/C32-1 -> 0 | F33: Aug 25 2025 | G33: 7980965 | H33: =G33/G32-1 -> -0.011164682
B34: Aug 18 2025 | C34: 58.94 | D34: =C34/C33-1 -> -0.092812067 | F34: Aug 18 2025 | G34: 8130685 | H34: =G34/G33-1 -> 0.018759636
B35: Aug 11 2025 | C35: 58.94 | D35: =C35/C34-1 -> 0 | F35: Aug 11 2025 | G35: 8059766 | H35: =G35/G34-1 -> -0.0087223893
B36: Aug 4 2025 | C36: 58.94 | D36: =C36/C35-1 -> 0 | F36: Aug 4 2025 | G36: 7985779 | H36: =G36/G35-1 -> -0.009179795
B37: Jul 28 2025 | C37: 58.94 | D37: =C37/C36-1 -> 0 | F37: Jul 28 2025 | G37: 8059991 | H37: =G37/G36-1 -> 0.0092930195
B38: Jul 21 2025 | C38: 58.94 | D38: =C38/C37-1 -> 0 | F38: Jul 21 2025 | G38: 8146309 | H38: =G38/G37-1 -> 0.010709441
B39: Jul 14 2025 | C39: 58.94 | D39: =C39/C38-1 -> 0 | F39: Jul 14 2025 | G39: 8175773 | H39: =G39/G38-1 -> 0.0036168527
B40: Jul 7 2025 | C40: 56.14 | D40: =C40/C39-1 -> -0.047505938 | F40: Jul 7 2025 | G40: 8250047 | H40: =G40/G39-1 -> 0.0090846456
B41: Jun 30 2025 | C41: 56.14 | D41: =C41/C40-1 -> 0 | F41: Jun 30 2025 | G41: 8343289 | H41: =G41/G40-1 -> 0.011301996
... B119: Jan 1 2024 | C119: 39.51 | D119: =C119/C118-1 -> 0 | F119: Jan 1 2024 | G119: 7202615 | H119: =G119/G118-1 -> -0.0074729445

Sheet Narbada beta
A7: Regression Beta - 2 Years Monthly
A9: Narbada Gems and Jewellery Ltd | E9: SENSEX Bse Return
A11: Date | B11: Close Price | C11: Return | E11: Date | F11: Close Price | G11: Return | N11: SUMMARY OUTPUT
A12: 25-01-2026 | B12: 56.75 | E12: 25-01-2026 | F12: 82269.78 | I12: Beta Drafting
A13: 18-01-2026 | B13: 58.2 | C13: =B13/B12-1 -> 0.025550661 | E13: 18-01-2026 | F13: 81537.7 | G13: =F13/F12-1 -> -0.0088985287 | N13: Regression Statistics
A14: 46327 | B14: 63.88 | C14: =B14/B13-1 -> 0.097594502 | E14: 46327 | F14: 83570.35 | G14: =F14/F13-1 -> 0.024928959 | N14: Multiple R | O14: 0.025130431
A15: 46113 | B15: 64.18 | C15: =B15/B14-1 -> 0.0046963056 | E15: 46113 | F15: 83576.24 | G15: =F15/F14-1 -> 7.0479542e-05 | I15: Levered Raw Beta | J15: =O28 -> 0.1212999 | N15: R Square | O15: 0.00063153856
A16: 28-12-2025 | B16: 63.33 | C16: =B16/B15-1 -> -0.013244001 | E16: 28-12-2025 | F16: 85762.01 | G16: =F16/F15-1 -> 0.026153007 | I16: Raw Beta Weight | J16: 0.75 | N16: Adjusted R Square | O16: -0.0088862563
A17: 21-12-2025 | B17: 69.3 | C17: =B17/B16-1 -> 0.094268119 | E17: 21-12-2025 | F17: 85041.45 | G17: =F17/F16-1 -> -0.0084018553 | N17: Standard Error | O17: 0.080448883
A18: 14-12-2025 | B18: 63.76 | C18: =B18/B17-1 -> -0.07994228 | E18: 14-12-2025 | F18: 84929.36 | G18: =F18/F17-1 -> -0.0013180631 | I18: Market Beta | J18: 1 | N18: Observations | O18: 107
A19: 45850 | B19: 67.53 | C19: =B19/B18-1 -> 0.05912798 | E19: 45850 | F19: 85267.66 | G19: =F19/F18-1 -> 0.0039833104 | I19: Market Beta Weight | J19: 0.25
A20: 30-11-2025 | B20: 69.39 | C20: =B20/B19-1 -> 0.027543314 | E20: 30-11-2025 | F20: 85712.37 | G20: =F20/F19-1 -> 0.0052154592 | N20: ANOVA
A21: 23-11-2025 | B21: 68.61 | C21: =B21/B20-1 -> -0.011240813 | E21: 23-11-2025 | F21: 85706.67 | G21: =F21/F20-1 -> -6.6501486e-05 | I21: Adjusted Beta | J21: =(J15*J16)+(J18*J19) -> 0.34097493 | O21: df | P21: SS | Q21: MS | R21: F | S21: Significance F
A22: 16-11-2025 | B22: 68.99 | C22: =B22/B21-1 -> 0.0055385512 | E22: 16-11-2025 | F22: 85231.92 | G22: =F22/F21-1 -> -0.0055392422 | N22: Regression | O22: 1 | P22: 0.00042944106 | Q22: 0.00042944106 | R22: 0.066353454 | S22: 0.79722624
A23: 45911 | B23: 73.31 | C23: =B23/B22-1 -> 0.062617771 | E23: 45911 | F23: 84562.78 | G23: =F23/F22-1 -> -0.0078508146 | N23: Residual | O23: 105 | P23: 0.67956238 | Q23: 0.0064720227
A24: 45699 | B24: 69.06 | C24: =B24/B23-1 -> -0.057972991 | E24: 45699 | F24: 83216.28 | G24: =F24/F23-1 -> -0.015923081 | N24: Total | O24: 106 | P24: 0.67999182
A25: 26-10-2025 | B25: 72.98 | C25: =B25/B24-1 -> 0.056762236 | E25: 26-10-2025 | F25: 83938.71 | G25: =F25/F24-1 -> 0.0086813542
A26: 19-10-2025 | B26: 72.7 | C26: =B26/B25-1 -> -0.0038366676 | E26: 19-10-2025 | F26: 84211.88 | G26: =F26/F25-1 -> 0.0032543984 | O26: Coefficients | P26: Standard Error | Q26: t Stat | R26: P-value | S26: Lower 95% | T26: Upper 95% | U26: Lower 95.0% | V26: Upper 95.0%
A27: 46001 | B27: 69.95 | C27: =B27/B26-1 -> -0.037826685 | E27: 46001 | F27: 83952.19 | G27: =F27/F26-1 -> -0.0030837692 | N27: Intercept | O27: 0.0017738734 | P27: 0.0077947052 | Q27: 0.22757414 | R27: 0.82041986 | S27: -0.013681587 | T27: 0.017229334 | U27: -0.013681587 | V27: 0.017229334
A28: 45787 | B28: 72.77 | C28: =B28/B27-1 -> 0.04031451 | E28: 45787 | F28: 82500.82 | G28: =F28/F27-1 -> -0.017288054 | N28: X Variable 1 | O28: 0.1212999 | P28: 0.47089999 | Q28: 0.25759164 | R28: 0.79722624 | S28: -0.81240779 | T28: 1.0550076 | U28: -0.81240779 | V28: 1.0550076
A29: 28-09-2025 | B29: 69.62 | C29: =B29/B28-1 -> -0.043287069 | E29: 28-09-2025 | F29: 81207.17 | G29: =F29/F28-1 -> -0.01568045
A30: 21-09-2025 | B30: 69.27 | C30: =B30/B29-1 -> -0.005027291 | E30: 21-09-2025 | F30: 80426.46 | G30: =F30/F29-1 -> -0.0096138063
A31: 14-09-2025 | B31: 70.07 | C31: =B31/B30-1 -> 0.011549011 | E31: 14-09-2025 | F31: 82626.23 | G31: =F31/F30-1 -> 0.027351322
A32: 45847 | B32: 71.89 | C32: =B32/B31-1 -> 0.025974026 | E32: 45847 | F32: 81904.7 | G32: =F32/F31-1 -> -0.008732457
A33: 31-08-2025 | B33: 72.06 | C33: =B33/B32-1 -> 0.0023647239 | E33: 31-08-2025 | F33: 80710.76 | G33: =F33/F32-1 -> -0.014577185
A34: 24-08-2025 | B34: 70.12 | C34: =B34/B33-1 -> -0.026922009 | E34: 24-08-2025 | F34: 79809.65 | G34: =F34/F33-1 -> -0.011164682
A35: 17-08-2025 | B35: 73.59 | C35: =B35/B34-1 -> 0.049486594 | E35: 17-08-2025 | F35: 81306.85 | G35: =F35/F34-1 -> 0.018759636
A36: 45938 | B36: 55 | C36: =B36/B35-1 -> -0.25261584 | E36: 45938 | F36: 80597.66 | G36: =F36/F35-1 -> -0.0087223893
A37: 45724 | B37: 52.75 | C37: =B37/B36-1 -> -0.040909091 | E37: 45724 | F37: 79857.79 | G37: =F37/F36-1 -> -0.009179795
A38: 27-07-2025 | B38: 50.3 | C38: =B38/B37-1 -> -0.046445498 | E38: 27-07-2025 | F38: 80599.91 | G38: =F38/F37-1 -> 0.0092930195
A39: 20-07-2025 | B39: 50.07 | C39: =B39/B38-1 -> -0.0045725646 | E39: 20-07-2025 | F39: 81463.09 | G39: =F39/F38-1 -> 0.010709441
A40: 13-07-2025 | B40: 51.15 | C40: =B40/B39-1 -> 0.021569802 | E40: 13-07-2025 | F40: 81757.73 | G40: =F40/F39-1 -> 0.0036168527
A41: 45815 | B41: 53.5 | C41: =B41/B40-1 -> 0.045943304 | E41: 45815 | F41: 82500.47 | G41: =F41/F40-1 -> 0.0090846456
A42: 29-06-2025 | B42: 53.77 | C42: =B42/B41-1 -> 0.005046729 | E42: 29-06-2025 | F42: 83432.89 | G42: =F42/F41-1 -> 0.011301996
A43: 22-06-2025 | B43: 54.9 | C43: =B43/B42-1 -> 0.021015436 | E43: 22-06-2025 | F43: 84058.9 | G43: =F43/F42-1 -> 0.0075031561
A44: 15-06-2025 | B44: 54.95 | C44: =B44/B43-1 -> 0.00091074681 | E44: 15-06-2025 | F44: 82408.17 | G44: =F44/F43-1 -> -0.019637778
A45: 45875 | B45: 54.8 | C45: =B45/B44-1 -> -0.0027297543 | E45: 45875 | F45: 81118.6 | G45: =F45/F44-1 -> -0.01564857
A46: 45663 | B46: 52.68 | C46: =B46/B45-1 -> -0.038686131 | E46: 45663 | F46: 82188.99 | G46: =F46/F45-1 -> 0.013195371
A47: 25-05-2025 | B47: 56.02 | C47: =B47/B46-1 -> 0.06340167 | E47: 25-05-2025 | F47: 81451.01 | G47: =F47/F46-1 -> -0.0089790616
A48: 18-05-2025 | B48: 54.09 | C48: =B48/B47-1 -> -0.034451981 | E48: 18-05-2025 | F48: 81721.08 | G48: =F48/F47-1 -> 0.0033157354
A49: 45966 | B49: 55.01 | C49: =B49/B48-1 -> 0.017008689 | E49: 45966 | F49: 82330.59 | G49: =F49/F48-1 -> 0.0074584183
A50: 45752 | B50: 54.49 | C50: =B50/B49-1 -> -0.0094528268 | E50: 45752 | F50: 79454.47 | G50: =F50/F49-1 -> -0.034933796
A51: 27-04-2025 | B51: 55.3 | C51: =B51/B50-1 -> 0.014865113 | E51: 27-04-2025 | F51: 80501.99 | G51: =F51/F50-1 -> 0.013183903
A52: 20-04-2025 | B52: 52.66 | C52: =B52/B51-1 -> -0.047739602 | E52: 20-04-2025 | F52: 79212.53 | G52: =F52/F51-1 -> -0.016017741
A53: 13-04-2025 | B53: 56.85 | C53: =B53/B52-1 -> 0.079567034 | E53: 13-04-2025 | F53: 78553.2 | G53: =F53/F52-1 -> -0.0083235569
A54: 45812 | B54: 53.95 | C54: =B54/B53-1 -> -0.051011434 | E54: 45812 | F54: 75157.26 | G54: =F54/F53-1 -> -0.043231084
A55: 30-03-2025 | B55: 55.02 | C55: =B55/B54-1 -> 0.019833179 | E55: 30-03-2025 | F55: 75364.69 | G55: =F55/F54-1 -> 0.0027599463
A56: 23-03-2025 | B56: 50.14 | C56: =B56/B55-1 -> -0.08869502 | E56: 23-03-2025 | F56: 77414.92 | G56: =F56/F55-1 -> 0.027204119
A57: 16-03-2025 | B57: 55.62 | C57: =B57/B56-1 -> 0.10929398 | E57: 16-03-2025 | F57: 76905.51 | G57: =F57/F56-1 -> -0.0065802561
A58: 45903 | B58: 53.05 | C58: =B58/B57-1 -> -0.046206401 | E58: 45903 | F58: 73828.91 | G58: =F58/F57-1 -> -0.040004936
A59: 45691 | B59: 55.91 | C59: =B59/B58-1 -> 0.053911404 | E59: 45691 | F59: 74332.58 | G59: =F59/F58-1 -> 0.0068221243
A60: 23-02-2025 | B60: 58.32 | C60: =B60/B59-1 -> 0.04310499 | E60: 23-02-2025 | F60: 73198.1 | G60: =F60/F59-1 -> -0.015262217
A61: 16-02-2025 | B61: 56.73 | C61: =B61/B60-1 -> -0.027263374 | E61: 16-02-2025 | F61: 75311.06 | G61: =F61/F60-1 -> 0.028866323
A62: 45902 | B62: 53.51 | C62: =B62/B61-1 -> -0.056760092 | E62: 45902 | F62: 75939.21 | G62: =F62/F61-1 -> 0.0083407404
A63: 45690 | B63: 60.95 | C63: =B63/B62-1 -> 0.13903943 | E63: 45690 | F63: 77860.19 | G63: =F63/F62-1 -> 0.025296286
A64: 26-01-2025 | B64: 62.5 | C64: =B64/B63-1 -> 0.025430681 | E64: 26-01-2025 | F64: 76190.46 | G64: =F64/F63-1 -> -0.021445234
A65: 19-01-2025 | B65: 62.45 | C65: =B65/B64-1 -> -0.0008 | E65: 19-01-2025 | F65: 76619.33 | G65: =F65/F64-1 -> 0.0056289199
A66: 45992 | B66: 62.28 | C66: =B66/B65-1 -> -0.0027221777 | E66: 45992 | F66: 77378.91 | G66: =F66/F65-1 -> 0.0099136863
A67: 45778 | B67: 63.11 | C67: =B67/B66-1 -> 0.013326911 | E67: 45778 | F67: 79223.11 | G67: =F67/F66-1 -> 0.023833368
A68: 29-12-2024 | B68: 65.59 | C68: =B68/B67-1 -> 0.039296466 | E68: 29-12-2024 | F68: 78699.07 | G68: =F68/F67-1 -> -0.0066147365
A69: 22-12-2024 | B69: 66.49 | C69: =B69/B68-1 -> 0.013721604 | E69: 22-12-2024 | F69: 78041.59 | G69: =F69/F68-1 -> -0.0083543554
A70: 15-12-2024 | B70: 65.56 | C70: =B70/B69-1 -> -0.013987066 | E70: 15-12-2024 | F70: 82133.12 | G70: =F70/F69-1 -> 0.052427558
A71: 45516 | B71: 69.74 | C71: =B71/B70-1 -> 0.063758389 | E71: 45516 | F71: 81709.12 | G71: =F71/F70-1 -> -0.0051623511
A72: 45303 | B72: 67.35 | C72: =B72/B71-1 -> -0.034270146 | E72: 45303 | F72: 79802.79 | G72: =F72/F71-1 -> -0.023330688
A73: 24-11-2024 | B73: 65 | C73: =B73/B72-1 -> -0.034892353 | E73: 24-11-2024 | F73: 79117.11 | G73: =F73/F72-1 -> -0.0085921808
A74: 17-11-2024 | B74: 60.56 | C74: =B74/B73-1 -> -0.068307692 | E74: 17-11-2024 | F74: 77580.31 | G74: =F74/F73-1 -> -0.01942437
A75: 45576 | B75: 60.1 | C75: =B75/B74-1 -> -0.0075957728 | E75: 45576 | F75: 79486.32 | G75: =F75/F74-1 -> 0.024568218
A76: 45362 | B76: 67.35 | C76: =B76/B75-1 -> 0.12063228 | E76: 45362 | F76: 79724.12 | G76: =F76/F75-1 -> 0.0029917098
A77: 27-10-2024 | B77: 74.32 | C77: =B77/B76-1 -> 0.10348924 | E77: 27-10-2024 | F77: 79402.29 | G77: =F77/F76-1 -> -0.0040367959
A78: 20-10-2024 | B78: 65.25 | C78: =B78/B77-1 -> -0.12203983 | E78: 20-10-2024 | F78: 81224.75 | G78: =F78/F77-1 -> 0.022952235
A79: 13-10-2024 | B79: 68.52 | C79: =B79/B78-1 -> 0.050114943 | E79: 13-10-2024 | F79: 81381.36 | G79: =F79/F78-1 -> 0.0019281069
A80: 45453 | B80: 73.91 | C80: =B80/B79-1 -> 0.078663164 | E80: 45453 | F80: 81688.45 | G80: =F80/F79-1 -> 0.0037734685
A81: 29-09-2024 | B81: 78.33 | C81: =B81/B80-1 -> 0.059802462 | E81: 29-09-2024 | F81: 85571.85 | G81: =F81/F80-1 -> 0.047539156
A82: 22-09-2024 | B82: 75.07 | C82: =B82/B81-1 -> -0.041618792 | E82: 22-09-2024 | F82: 84544.31 | G82: =F82/F81-1 -> -0.012007921
A83: 15-09-2024 | B83: 76.82 | C83: =B83/B82-1 -> 0.023311576 | E83: 15-09-2024 | F83: 82890.94 | G83: =F83/F82-1 -> -0.019556254
A84: 45513 | B84: 73.92 | C84: =B84/B83-1 -> -0.037750586 | E84: 45513 | F84: 81183.93 | G84: =F84/F83-1 -> -0.020593445
A85: 45300 | B85: 66.59 | C85: =B85/B84-1 -> -0.099161255 | E85: 45300 | F85: 82365.77 | G85: =F85/F84-1 -> 0.014557561
A86: 25-08-2024 | B86: 76.91 | C86: =B86/B85-1 -> 0.15497822 | E86: 25-08-2024 | F86: 81086.21 | G86: =F86/F85-1 -> -0.015535094
A87: 18-08-2024 | B87: 81.76 | C87: =B87/B86-1 -> 0.06306072 | E87: 18-08-2024 | F87: 80436.84 | G87: =F87/F86-1 -> -0.0080083901
A88: 45604 | B88: 56.24 | C88: =B88/B87-1 -> -0.31213307 | E88: 45604 | F88: 79705.91 | G88: =F88/F87-1 -> -0.0090870054
A89: 45390 | B89: 55.21 | C89: =B89/B88-1 -> -0.018314367 | E89: 45390 | F89: 80981.95 | G89: =F89/F88-1 -> 0.016009352
A90: 28-07-2024 | B90: 54.11 | C90: =B90/B89-1 -> -0.019923927 | E90: 28-07-2024 | F90: 81332.72 | G90: =F90/F89-1 -> 0.004331459
A91: 21-07-2024 | B91: 55.87 | C91: =B91/B90-1 -> 0.032526335 | E91: 21-07-2024 | F91: 80604.65 | G91: =F91/F90-1 -> -0.0089517478
A92: 14-07-2024 | B92: 55.5 | C92: =B92/B91-1 -> -0.0066225166 | E92: 14-07-2024 | F92: 80519.34 | G92: =F92/F91-1 -> -0.0010583757
A93: 45480 | B93: 57.17 | C93: =B93/B92-1 -> 0.03009009 | E93: 45480 | F93: 79996.6 | G93: =F93/F92-1 -> -0.0064921049
A94: 30-06-2024 | B94: 57.78 | C94: =B94/B93-1 -> 0.010669932 | E94: 30-06-2024 | F94: 79032.73 | G94: =F94/F93-1 -> -0.012048887
A95: 23-06-2024 | B95: 55.91 | C95: =B95/B94-1 -> -0.03236414 | E95: 23-06-2024 | F95: 77209.9 | G95: =F95/F94-1 -> -0.023064242
A96: 16-06-2024 | B96: 58.88 | C96: =B96/B95-1 -> 0.053121087 | E96: 16-06-2024 | F96: 76992.77 | G96: =F96/F95-1 -> -0.0028122041
A97: 45541 | B97: 58.06 | C97: =B97/B96-1 -> -0.01392663 | E97: 45541 | F97: 76693.36 | G97: =F97/F96-1 -> -0.0038888067
A98: 45328 | B98: 58.46 | C98: =B98/B97-1 -> 0.0068894247 | E98: 45328 | F98: 73961.31 | G98: =F98/F97-1 -> -0.035623032
A99: 26-05-2024 | B99: 58.21 | C99: =B99/B98-1 -> -0.0042764283 | E99: 26-05-2024 | F99: 75410.39 | G99: =F99/F98-1 -> 0.019592406
A100: 19-05-2024 | B100: 68.1 | C100: =B100/B99-1 -> 0.16990208 | E100: 19-05-2024 | F100: 74005.94 | G100: =F100/F99-1 -> -0.018624091
A101: 45631 | B101: 69.95 | C101: =B101/B100-1 -> 0.027165932 | E101: 45631 | F101: 72664.47 | G101: =F101/F100-1 -> -0.018126518
A102: 45417 | B102: 71 | C102: =B102/B101-1 -> 0.015010722 | E102: 45417 | F102: 73878.15 | G102: =F102/F101-1 -> 0.016702523
A103: 28-04-2024 | B103: 67.6 | C103: =B103/B102-1 -> -0.047887324 | E103: 28-04-2024 | F103: 73730.16 | G103: =F103/F102-1 -> -0.0020031633
A104: 21-04-2024 | B104: 70.5 | C104: =B104/B103-1 -> 0.042899408 | E104: 21-04-2024 | F104: 73088.33 | G104: =F104/F103-1 -> -0.0087051215
A105: 14-04-2024 | B105: 73.2 | C105: =B105/B104-1 -> 0.038297872 | E105: 14-04-2024 | F105: 74244.9 | G105: =F105/F104-1 -> 0.015824277
A106: 45477 | B106: 73.29 | C106: =B106/B105-1 -> 0.0012295082 | E106: 45477 | F106: 74248.22 | G106: =F106/F105-1 -> 4.4716876e-05
A107: 31-03-2024 | B107: 72.65 | C107: =B107/B106-1 -> -0.0087324328 | E107: 31-03-2024 | F107: 73651.35 | G107: =F107/F106-1 -> -0.0080388459
A108: 24-03-2024 | B108: 64.01 | C108: =B108/B107-1 -> -0.11892636 | E108: 24-03-2024 | F108: 72831.94 | G108: =F108/F107-1 -> -0.011125526
...
